<?xml version="1.0" encoding="utf-8"?>
<Config>
  <HuiGuiDayZhiGou ID="1" HuoDongLevel="1" TotalYuanBao="0,-1" Day="1" Price="1|11|6775" GoodsID1="2001,388,1,0,0,0,0|2002,388,1,0,0,0,0|2003,388,1,0,0,0,0|51419,18,0,0,0,0,0" GoodsID2="" Max="88" />
  <HuiGuiDayZhiGou ID="2" HuoDongLevel="1" TotalYuanBao="0,-1" Day="1" Price="1|11|6776" GoodsID1="2030,388,1,0,0,0,0|51419,18,0,0,0,0,0" GoodsID2="" Max="88" />
  <HuiGuiDayZhiGou ID="3" HuoDongLevel="1" TotalYuanBao="0,-1" Day="1" Price="1|2|6777" GoodsID1="2017,2888,1,0,0,0,0|2016,2388,1,0,0,0,0|51419,18,0,0,0,0,0" GoodsID2="" Max="88" />
  <HuiGuiDayZhiGou ID="4" HuoDongLevel="1" TotalYuanBao="0,-1" Day="1" Price="1|2|6778" GoodsID1="5050,2588,1,0,0,0,0|50305,18,1,0,0,0,0|50017,588,1,0,0,0,0|51419,18,0,0,0,0,0" GoodsID2="" Max="88" />
  <HuiGuiDayZhiGou ID="5" HuoDongLevel="1" TotalYuanBao="0,-1" Day="1" Price="1|14|6779" GoodsID1="2100,2588,1,0,0,0,0|5050,3888,1,0,0,0,0|5031,258,1,0,0,0,0|5041,258,1,0,0,0,0" GoodsID2="" Max="88" />
  <HuiGuiDayZhiGou ID="6" HuoDongLevel="1" TotalYuanBao="0,-1" Day="1" Price="1|16|6780" GoodsID1="7050,9888,1,0,0,0,0|50015,1588,1,0,0,0,0|5120,1088,1,0,0,0,0|51419,18,0,0,0,0,0" GoodsID2="" Max="88" />
  <HuiGuiDayZhiGou ID="7" HuoDongLevel="1" TotalYuanBao="0,-1" Day="1" Price="1|12|6781" GoodsID1="5120,628,1,0,0,0,0|7050,1888,1,0,0,0,0|51419,38,0,0,0,0,0" GoodsID2="" Max="88" />
  <HuiGuiDayZhiGou ID="8" HuoDongLevel="1" TotalYuanBao="0,-1" Day="1" Price="1|2|6782" GoodsID1="5312,108,1,0,0,0,0|7007,1688,1,0,0,0,0" GoodsID2="" Max="88" />
  <HuiGuiDayZhiGou ID="9" HuoDongLevel="1" TotalYuanBao="0,-1" Day="1" Price="1|14|6783" GoodsID1="63222,1,1,0,0,0,0|2103,688,1,0,0,0,0|2104,118,1,0,0,0,0" GoodsID2="" Max="88" />
  <HuiGuiDayZhiGou ID="10" HuoDongLevel="1" TotalYuanBao="0,-1" Day="1" Price="1|14|6784" GoodsID1="5331,100,1,0,0,0,0|5110,100,1,0,0,0,0|5220,100,1,0,0,0,0" GoodsID2="" Max="88" />
  <HuiGuiDayZhiGou ID="11" HuoDongLevel="1" TotalYuanBao="0,-1" Day="1" Price="1|16|6785" GoodsID1="5250,1688,1,0,0,0,0|2005,128,1,0,0,0,0" GoodsID2="" Max="88" />
  <HuiGuiDayZhiGou ID="12" HuoDongLevel="1" TotalYuanBao="0,-1" Day="1" Price="1|16|6786" GoodsID1="5284,288,1,0,0,0,0|5271,188,1,0,0,0,0" GoodsID2="" Max="88" />
  <HuiGuiDayZhiGou ID="13" HuoDongLevel="1" TotalYuanBao="0,-1" Day="1" Price="1|16|6787" GoodsID1="63215,1,1,0,0,0,0|51275,188,0,0,0,0,0" GoodsID2="" Max="88" />
  <HuiGuiDayZhiGou ID="14" HuoDongLevel="1" TotalYuanBao="0,-1" Day="1" Price="1|16|6788" GoodsID1="63201,1,1,0,0,0,0|51275,188,0,0,0,0,0" GoodsID2="" Max="88" />
  <HuiGuiDayZhiGou ID="15" HuoDongLevel="1" TotalYuanBao="0,-1" Day="1" Price="1|16|6789" GoodsID1="63203,1,1,0,0,0,0|51275,188,0,0,0,0,0" GoodsID2="" Max="88" />
  <HuiGuiDayZhiGou ID="16" HuoDongLevel="1" TotalYuanBao="0,-1" Day="1" Price="1|19|6790" GoodsID1="63216,1,1,0,0,0,0" GoodsID2="" Max="88" />
  <HuiGuiDayZhiGou ID="17" HuoDongLevel="1" TotalYuanBao="0,-1" Day="1" Price="1|19|6791" GoodsID1="63202,1,1,0,0,0,0" GoodsID2="" Max="88" />
  <HuiGuiDayZhiGou ID="18" HuoDongLevel="1" TotalYuanBao="0,-1" Day="2" Price="1|11|6792" GoodsID1="2001,388,1,0,0,0,0|2002,388,1,0,0,0,0|2003,388,1,0,0,0,0|51419,18,0,0,0,0,0" GoodsID2="" Max="88" />
  <HuiGuiDayZhiGou ID="19" HuoDongLevel="1" TotalYuanBao="0,-1" Day="2" Price="1|11|6793" GoodsID1="2030,388,1,0,0,0,0|51419,18,0,0,0,0,0" GoodsID2="" Max="88" />
  <HuiGuiDayZhiGou ID="20" HuoDongLevel="1" TotalYuanBao="0,-1" Day="2" Price="1|2|6794" GoodsID1="2017,2888,1,0,0,0,0|2016,2388,1,0,0,0,0|51419,18,0,0,0,0,0" GoodsID2="" Max="88" />
  <HuiGuiDayZhiGou ID="21" HuoDongLevel="1" TotalYuanBao="0,-1" Day="2" Price="1|2|6795" GoodsID1="5050,2588,1,0,0,0,0|50305,18,1,0,0,0,0|50017,588,1,0,0,0,0|51419,18,0,0,0,0,0" GoodsID2="" Max="88" />
  <HuiGuiDayZhiGou ID="22" HuoDongLevel="1" TotalYuanBao="0,-1" Day="2" Price="1|14|6796" GoodsID1="2100,2588,1,0,0,0,0|5050,3888,1,0,0,0,0|5031,258,1,0,0,0,0|5041,258,1,0,0,0,0" GoodsID2="" Max="88" />
  <HuiGuiDayZhiGou ID="23" HuoDongLevel="1" TotalYuanBao="0,-1" Day="2" Price="1|16|6797" GoodsID1="7050,9888,1,0,0,0,0|50015,1588,1,0,0,0,0|5120,1088,1,0,0,0,0|51419,18,0,0,0,0,0" GoodsID2="" Max="88" />
  <HuiGuiDayZhiGou ID="24" HuoDongLevel="1" TotalYuanBao="0,-1" Day="2" Price="1|12|6798" GoodsID1="5120,628,1,0,0,0,0|7050,1888,1,0,0,0,0|51419,38,0,0,0,0,0" GoodsID2="" Max="88" />
  <HuiGuiDayZhiGou ID="25" HuoDongLevel="1" TotalYuanBao="0,-1" Day="2" Price="1|2|6799" GoodsID1="5312,108,1,0,0,0,0|7007,1688,1,0,0,0,0" GoodsID2="" Max="88" />
  <HuiGuiDayZhiGou ID="26" HuoDongLevel="1" TotalYuanBao="0,-1" Day="2" Price="1|14|6800" GoodsID1="63222,1,1,0,0,0,0|2103,688,1,0,0,0,0|2104,118,1,0,0,0,0" GoodsID2="" Max="88" />
  <HuiGuiDayZhiGou ID="27" HuoDongLevel="1" TotalYuanBao="0,-1" Day="2" Price="1|14|6801" GoodsID1="5331,100,1,0,0,0,0|5110,100,1,0,0,0,0|5220,100,1,0,0,0,0" GoodsID2="" Max="88" />
  <HuiGuiDayZhiGou ID="28" HuoDongLevel="1" TotalYuanBao="0,-1" Day="2" Price="1|16|6802" GoodsID1="5250,1688,1,0,0,0,0|2005,128,1,0,0,0,0" GoodsID2="" Max="88" />
  <HuiGuiDayZhiGou ID="29" HuoDongLevel="1" TotalYuanBao="0,-1" Day="2" Price="1|16|6803" GoodsID1="5284,288,1,0,0,0,0|5271,188,1,0,0,0,0" GoodsID2="" Max="88" />
  <HuiGuiDayZhiGou ID="30" HuoDongLevel="1" TotalYuanBao="0,-1" Day="2" Price="1|16|6804" GoodsID1="63215,1,1,0,0,0,0|51275,188,0,0,0,0,0" GoodsID2="" Max="88" />
  <HuiGuiDayZhiGou ID="31" HuoDongLevel="1" TotalYuanBao="0,-1" Day="2" Price="1|16|6805" GoodsID1="63201,1,1,0,0,0,0|51275,188,0,0,0,0,0" GoodsID2="" Max="88" />
  <HuiGuiDayZhiGou ID="32" HuoDongLevel="1" TotalYuanBao="0,-1" Day="2" Price="1|16|6806" GoodsID1="63203,1,1,0,0,0,0|51275,188,0,0,0,0,0" GoodsID2="" Max="88" />
  <HuiGuiDayZhiGou ID="33" HuoDongLevel="1" TotalYuanBao="0,-1" Day="2" Price="1|19|6807" GoodsID1="63216,1,1,0,0,0,0" GoodsID2="" Max="88" />
  <HuiGuiDayZhiGou ID="34" HuoDongLevel="1" TotalYuanBao="0,-1" Day="2" Price="1|19|6808" GoodsID1="63202,1,1,0,0,0,0" GoodsID2="" Max="88" />
  <HuiGuiDayZhiGou ID="35" HuoDongLevel="1" TotalYuanBao="0,-1" Day="3" Price="1|11|6809" GoodsID1="2001,388,1,0,0,0,0|2002,388,1,0,0,0,0|2003,388,1,0,0,0,0|51419,18,0,0,0,0,0" GoodsID2="" Max="88" />
  <HuiGuiDayZhiGou ID="36" HuoDongLevel="1" TotalYuanBao="0,-1" Day="3" Price="1|11|6810" GoodsID1="2030,388,1,0,0,0,0|51419,18,0,0,0,0,0" GoodsID2="" Max="88" />
  <HuiGuiDayZhiGou ID="37" HuoDongLevel="1" TotalYuanBao="0,-1" Day="3" Price="1|2|6811" GoodsID1="2017,2888,1,0,0,0,0|2016,2388,1,0,0,0,0|51419,18,0,0,0,0,0" GoodsID2="" Max="88" />
  <HuiGuiDayZhiGou ID="38" HuoDongLevel="1" TotalYuanBao="0,-1" Day="3" Price="1|2|6812" GoodsID1="5050,2588,1,0,0,0,0|50305,18,1,0,0,0,0|50017,588,1,0,0,0,0|51419,18,0,0,0,0,0" GoodsID2="" Max="88" />
  <HuiGuiDayZhiGou ID="39" HuoDongLevel="1" TotalYuanBao="0,-1" Day="3" Price="1|14|6813" GoodsID1="2100,2588,1,0,0,0,0|5050,3888,1,0,0,0,0|5031,258,1,0,0,0,0|5041,258,1,0,0,0,0" GoodsID2="" Max="88" />
  <HuiGuiDayZhiGou ID="40" HuoDongLevel="1" TotalYuanBao="0,-1" Day="3" Price="1|16|6814" GoodsID1="7050,9888,1,0,0,0,0|50015,1588,1,0,0,0,0|5120,1088,1,0,0,0,0|51419,18,0,0,0,0,0" GoodsID2="" Max="88" />
  <HuiGuiDayZhiGou ID="41" HuoDongLevel="1" TotalYuanBao="0,-1" Day="3" Price="1|12|6815" GoodsID1="5120,628,1,0,0,0,0|7050,1888,1,0,0,0,0|51419,38,0,0,0,0,0" GoodsID2="" Max="88" />
  <HuiGuiDayZhiGou ID="42" HuoDongLevel="1" TotalYuanBao="0,-1" Day="3" Price="1|2|6816" GoodsID1="5312,108,1,0,0,0,0|7007,1688,1,0,0,0,0" GoodsID2="" Max="88" />
  <HuiGuiDayZhiGou ID="43" HuoDongLevel="1" TotalYuanBao="0,-1" Day="3" Price="1|14|6817" GoodsID1="63222,1,1,0,0,0,0|2103,688,1,0,0,0,0|2104,118,1,0,0,0,0" GoodsID2="" Max="88" />
  <HuiGuiDayZhiGou ID="44" HuoDongLevel="1" TotalYuanBao="0,-1" Day="3" Price="1|14|6818" GoodsID1="5331,100,1,0,0,0,0|5110,100,1,0,0,0,0|5220,100,1,0,0,0,0" GoodsID2="" Max="88" />
  <HuiGuiDayZhiGou ID="45" HuoDongLevel="1" TotalYuanBao="0,-1" Day="3" Price="1|16|6819" GoodsID1="5250,1688,1,0,0,0,0|2005,128,1,0,0,0,0" GoodsID2="" Max="88" />
  <HuiGuiDayZhiGou ID="46" HuoDongLevel="1" TotalYuanBao="0,-1" Day="3" Price="1|16|6820" GoodsID1="5284,288,1,0,0,0,0|5271,188,1,0,0,0,0" GoodsID2="" Max="88" />
  <HuiGuiDayZhiGou ID="47" HuoDongLevel="1" TotalYuanBao="0,-1" Day="3" Price="1|16|6821" GoodsID1="63215,1,1,0,0,0,0|51275,188,0,0,0,0,0" GoodsID2="" Max="88" />
  <HuiGuiDayZhiGou ID="48" HuoDongLevel="1" TotalYuanBao="0,-1" Day="3" Price="1|16|6822" GoodsID1="63201,1,1,0,0,0,0|51275,188,0,0,0,0,0" GoodsID2="" Max="88" />
  <HuiGuiDayZhiGou ID="49" HuoDongLevel="1" TotalYuanBao="0,-1" Day="3" Price="1|16|6823" GoodsID1="63203,1,1,0,0,0,0|51275,188,0,0,0,0,0" GoodsID2="" Max="88" />
  <HuiGuiDayZhiGou ID="50" HuoDongLevel="1" TotalYuanBao="0,-1" Day="3" Price="1|19|6824" GoodsID1="63216,1,1,0,0,0,0" GoodsID2="" Max="88" />
  <HuiGuiDayZhiGou ID="51" HuoDongLevel="1" TotalYuanBao="0,-1" Day="3" Price="1|19|6825" GoodsID1="63202,1,1,0,0,0,0" GoodsID2="" Max="88" />
  <HuiGuiDayZhiGou ID="52" HuoDongLevel="1" TotalYuanBao="0,-1" Day="4" Price="1|11|6826" GoodsID1="2001,388,1,0,0,0,0|2002,388,1,0,0,0,0|2003,388,1,0,0,0,0|51419,18,0,0,0,0,0" GoodsID2="" Max="88" />
  <HuiGuiDayZhiGou ID="53" HuoDongLevel="1" TotalYuanBao="0,-1" Day="4" Price="1|11|6827" GoodsID1="2030,388,1,0,0,0,0|51419,18,0,0,0,0,0" GoodsID2="" Max="88" />
  <HuiGuiDayZhiGou ID="54" HuoDongLevel="1" TotalYuanBao="0,-1" Day="4" Price="1|2|6828" GoodsID1="2017,2888,1,0,0,0,0|2016,2388,1,0,0,0,0|51419,18,0,0,0,0,0" GoodsID2="" Max="88" />
  <HuiGuiDayZhiGou ID="55" HuoDongLevel="1" TotalYuanBao="0,-1" Day="4" Price="1|2|6829" GoodsID1="5050,2588,1,0,0,0,0|50305,18,1,0,0,0,0|50017,588,1,0,0,0,0|51419,18,0,0,0,0,0" GoodsID2="" Max="88" />
  <HuiGuiDayZhiGou ID="56" HuoDongLevel="1" TotalYuanBao="0,-1" Day="4" Price="1|14|6830" GoodsID1="2100,2588,1,0,0,0,0|5050,3888,1,0,0,0,0|5031,258,1,0,0,0,0|5041,258,1,0,0,0,0" GoodsID2="" Max="88" />
  <HuiGuiDayZhiGou ID="57" HuoDongLevel="1" TotalYuanBao="0,-1" Day="4" Price="1|16|6831" GoodsID1="7050,9888,1,0,0,0,0|50015,1588,1,0,0,0,0|5120,1088,1,0,0,0,0|51419,18,0,0,0,0,0" GoodsID2="" Max="88" />
  <HuiGuiDayZhiGou ID="58" HuoDongLevel="1" TotalYuanBao="0,-1" Day="4" Price="1|12|6832" GoodsID1="5120,628,1,0,0,0,0|7050,1888,1,0,0,0,0|51419,38,0,0,0,0,0" GoodsID2="" Max="88" />
  <HuiGuiDayZhiGou ID="59" HuoDongLevel="1" TotalYuanBao="0,-1" Day="4" Price="1|2|6833" GoodsID1="5312,108,1,0,0,0,0|7007,1688,1,0,0,0,0" GoodsID2="" Max="88" />
  <HuiGuiDayZhiGou ID="60" HuoDongLevel="1" TotalYuanBao="0,-1" Day="4" Price="1|14|6834" GoodsID1="63222,1,1,0,0,0,0|2103,688,1,0,0,0,0|2104,118,1,0,0,0,0" GoodsID2="" Max="88" />
  <HuiGuiDayZhiGou ID="61" HuoDongLevel="1" TotalYuanBao="0,-1" Day="4" Price="1|14|6835" GoodsID1="5331,100,1,0,0,0,0|5110,100,1,0,0,0,0|5220,100,1,0,0,0,0" GoodsID2="" Max="88" />
  <HuiGuiDayZhiGou ID="62" HuoDongLevel="1" TotalYuanBao="0,-1" Day="4" Price="1|16|6836" GoodsID1="5250,1688,1,0,0,0,0|2005,128,1,0,0,0,0" GoodsID2="" Max="88" />
  <HuiGuiDayZhiGou ID="63" HuoDongLevel="1" TotalYuanBao="0,-1" Day="4" Price="1|16|6837" GoodsID1="5284,288,1,0,0,0,0|5271,188,1,0,0,0,0" GoodsID2="" Max="88" />
  <HuiGuiDayZhiGou ID="64" HuoDongLevel="1" TotalYuanBao="0,-1" Day="4" Price="1|16|6838" GoodsID1="63215,1,1,0,0,0,0|51275,188,0,0,0,0,0" GoodsID2="" Max="88" />
  <HuiGuiDayZhiGou ID="65" HuoDongLevel="1" TotalYuanBao="0,-1" Day="4" Price="1|16|6839" GoodsID1="63201,1,1,0,0,0,0|51275,188,0,0,0,0,0" GoodsID2="" Max="88" />
  <HuiGuiDayZhiGou ID="66" HuoDongLevel="1" TotalYuanBao="0,-1" Day="4" Price="1|16|6840" GoodsID1="63203,1,1,0,0,0,0|51275,188,0,0,0,0,0" GoodsID2="" Max="88" />
  <HuiGuiDayZhiGou ID="67" HuoDongLevel="1" TotalYuanBao="0,-1" Day="4" Price="1|19|6841" GoodsID1="63216,1,1,0,0,0,0" GoodsID2="" Max="88" />
  <HuiGuiDayZhiGou ID="68" HuoDongLevel="1" TotalYuanBao="0,-1" Day="4" Price="1|19|6842" GoodsID1="63202,1,1,0,0,0,0" GoodsID2="" Max="88" />
  <HuiGuiDayZhiGou ID="69" HuoDongLevel="1" TotalYuanBao="0,-1" Day="5" Price="1|11|6843" GoodsID1="2001,388,1,0,0,0,0|2002,388,1,0,0,0,0|2003,388,1,0,0,0,0|51419,18,0,0,0,0,0" GoodsID2="" Max="88" />
  <HuiGuiDayZhiGou ID="70" HuoDongLevel="1" TotalYuanBao="0,-1" Day="5" Price="1|11|6844" GoodsID1="2030,388,1,0,0,0,0|51419,18,0,0,0,0,0" GoodsID2="" Max="88" />
  <HuiGuiDayZhiGou ID="71" HuoDongLevel="1" TotalYuanBao="0,-1" Day="5" Price="1|2|6845" GoodsID1="2017,2888,1,0,0,0,0|2016,2388,1,0,0,0,0|51419,18,0,0,0,0,0" GoodsID2="" Max="88" />
  <HuiGuiDayZhiGou ID="72" HuoDongLevel="1" TotalYuanBao="0,-1" Day="5" Price="1|2|6846" GoodsID1="5050,2588,1,0,0,0,0|50305,18,1,0,0,0,0|50017,588,1,0,0,0,0|51419,18,0,0,0,0,0" GoodsID2="" Max="88" />
  <HuiGuiDayZhiGou ID="73" HuoDongLevel="1" TotalYuanBao="0,-1" Day="5" Price="1|14|6847" GoodsID1="2100,2588,1,0,0,0,0|5050,3888,1,0,0,0,0|5031,258,1,0,0,0,0|5041,258,1,0,0,0,0" GoodsID2="" Max="88" />
  <HuiGuiDayZhiGou ID="74" HuoDongLevel="1" TotalYuanBao="0,-1" Day="5" Price="1|16|6848" GoodsID1="7050,9888,1,0,0,0,0|50015,1588,1,0,0,0,0|5120,1088,1,0,0,0,0|51419,18,0,0,0,0,0" GoodsID2="" Max="88" />
  <HuiGuiDayZhiGou ID="75" HuoDongLevel="1" TotalYuanBao="0,-1" Day="5" Price="1|12|6849" GoodsID1="5120,628,1,0,0,0,0|7050,1888,1,0,0,0,0|51419,38,0,0,0,0,0" GoodsID2="" Max="88" />
  <HuiGuiDayZhiGou ID="76" HuoDongLevel="1" TotalYuanBao="0,-1" Day="5" Price="1|2|6850" GoodsID1="5312,108,1,0,0,0,0|7007,1688,1,0,0,0,0" GoodsID2="" Max="88" />
  <HuiGuiDayZhiGou ID="77" HuoDongLevel="1" TotalYuanBao="0,-1" Day="5" Price="1|14|6851" GoodsID1="63222,1,1,0,0,0,0|2103,688,1,0,0,0,0|2104,118,1,0,0,0,0" GoodsID2="" Max="88" />
  <HuiGuiDayZhiGou ID="78" HuoDongLevel="1" TotalYuanBao="0,-1" Day="5" Price="1|14|6852" GoodsID1="5331,100,1,0,0,0,0|5110,100,1,0,0,0,0|5220,100,1,0,0,0,0" GoodsID2="" Max="88" />
  <HuiGuiDayZhiGou ID="79" HuoDongLevel="1" TotalYuanBao="0,-1" Day="5" Price="1|16|6853" GoodsID1="5250,1688,1,0,0,0,0|2005,128,1,0,0,0,0" GoodsID2="" Max="88" />
  <HuiGuiDayZhiGou ID="80" HuoDongLevel="1" TotalYuanBao="0,-1" Day="5" Price="1|16|6854" GoodsID1="5284,288,1,0,0,0,0|5271,188,1,0,0,0,0" GoodsID2="" Max="88" />
  <HuiGuiDayZhiGou ID="81" HuoDongLevel="1" TotalYuanBao="0,-1" Day="5" Price="1|16|6855" GoodsID1="63215,1,1,0,0,0,0|51275,188,0,0,0,0,0" GoodsID2="" Max="88" />
  <HuiGuiDayZhiGou ID="82" HuoDongLevel="1" TotalYuanBao="0,-1" Day="5" Price="1|16|6856" GoodsID1="63201,1,1,0,0,0,0|51275,188,0,0,0,0,0" GoodsID2="" Max="88" />
  <HuiGuiDayZhiGou ID="83" HuoDongLevel="1" TotalYuanBao="0,-1" Day="5" Price="1|16|6857" GoodsID1="63203,1,1,0,0,0,0|51275,188,0,0,0,0,0" GoodsID2="" Max="88" />
  <HuiGuiDayZhiGou ID="84" HuoDongLevel="1" TotalYuanBao="0,-1" Day="5" Price="1|19|6858" GoodsID1="63216,1,1,0,0,0,0" GoodsID2="" Max="88" />
  <HuiGuiDayZhiGou ID="85" HuoDongLevel="1" TotalYuanBao="0,-1" Day="5" Price="1|19|6859" GoodsID1="63202,1,1,0,0,0,0" GoodsID2="" Max="88" />
  <HuiGuiDayZhiGou ID="86" HuoDongLevel="1" TotalYuanBao="0,-1" Day="6" Price="1|11|6860" GoodsID1="2001,388,1,0,0,0,0|2002,388,1,0,0,0,0|2003,388,1,0,0,0,0|51419,18,0,0,0,0,0" GoodsID2="" Max="88" />
  <HuiGuiDayZhiGou ID="87" HuoDongLevel="1" TotalYuanBao="0,-1" Day="6" Price="1|11|6861" GoodsID1="2030,388,1,0,0,0,0|51419,18,0,0,0,0,0" GoodsID2="" Max="88" />
  <HuiGuiDayZhiGou ID="88" HuoDongLevel="1" TotalYuanBao="0,-1" Day="6" Price="1|2|6862" GoodsID1="2017,2888,1,0,0,0,0|2016,2388,1,0,0,0,0|51419,18,0,0,0,0,0" GoodsID2="" Max="88" />
  <HuiGuiDayZhiGou ID="89" HuoDongLevel="1" TotalYuanBao="0,-1" Day="6" Price="1|2|6863" GoodsID1="5050,2588,1,0,0,0,0|50305,18,1,0,0,0,0|50017,588,1,0,0,0,0|51419,18,0,0,0,0,0" GoodsID2="" Max="88" />
  <HuiGuiDayZhiGou ID="90" HuoDongLevel="1" TotalYuanBao="0,-1" Day="6" Price="1|14|6864" GoodsID1="2100,2588,1,0,0,0,0|5050,3888,1,0,0,0,0|5031,258,1,0,0,0,0|5041,258,1,0,0,0,0" GoodsID2="" Max="88" />
  <HuiGuiDayZhiGou ID="91" HuoDongLevel="1" TotalYuanBao="0,-1" Day="6" Price="1|16|6865" GoodsID1="7050,9888,1,0,0,0,0|50015,1588,1,0,0,0,0|5120,1088,1,0,0,0,0|51419,18,0,0,0,0,0" GoodsID2="" Max="88" />
  <HuiGuiDayZhiGou ID="92" HuoDongLevel="1" TotalYuanBao="0,-1" Day="6" Price="1|12|6866" GoodsID1="5120,628,1,0,0,0,0|7050,1888,1,0,0,0,0|51419,38,0,0,0,0,0" GoodsID2="" Max="88" />
  <HuiGuiDayZhiGou ID="93" HuoDongLevel="1" TotalYuanBao="0,-1" Day="6" Price="1|2|6867" GoodsID1="5312,108,1,0,0,0,0|7007,1688,1,0,0,0,0" GoodsID2="" Max="88" />
  <HuiGuiDayZhiGou ID="94" HuoDongLevel="1" TotalYuanBao="0,-1" Day="6" Price="1|14|6868" GoodsID1="63222,1,1,0,0,0,0|2103,688,1,0,0,0,0|2104,118,1,0,0,0,0" GoodsID2="" Max="88" />
  <HuiGuiDayZhiGou ID="95" HuoDongLevel="1" TotalYuanBao="0,-1" Day="6" Price="1|14|6869" GoodsID1="5331,100,1,0,0,0,0|5110,100,1,0,0,0,0|5220,100,1,0,0,0,0" GoodsID2="" Max="88" />
  <HuiGuiDayZhiGou ID="96" HuoDongLevel="1" TotalYuanBao="0,-1" Day="6" Price="1|16|6870" GoodsID1="5250,1688,1,0,0,0,0|2005,128,1,0,0,0,0" GoodsID2="" Max="88" />
  <HuiGuiDayZhiGou ID="97" HuoDongLevel="1" TotalYuanBao="0,-1" Day="6" Price="1|16|6871" GoodsID1="5284,288,1,0,0,0,0|5271,188,1,0,0,0,0" GoodsID2="" Max="88" />
  <HuiGuiDayZhiGou ID="98" HuoDongLevel="1" TotalYuanBao="0,-1" Day="6" Price="1|16|6872" GoodsID1="63215,1,1,0,0,0,0|51275,188,0,0,0,0,0" GoodsID2="" Max="88" />
  <HuiGuiDayZhiGou ID="99" HuoDongLevel="1" TotalYuanBao="0,-1" Day="6" Price="1|16|6873" GoodsID1="63201,1,1,0,0,0,0|51275,188,0,0,0,0,0" GoodsID2="" Max="88" />
  <HuiGuiDayZhiGou ID="100" HuoDongLevel="1" TotalYuanBao="0,-1" Day="6" Price="1|16|6874" GoodsID1="63203,1,1,0,0,0,0|51275,188,0,0,0,0,0" GoodsID2="" Max="88" />
  <HuiGuiDayZhiGou ID="101" HuoDongLevel="1" TotalYuanBao="0,-1" Day="6" Price="1|19|6875" GoodsID1="63216,1,1,0,0,0,0" GoodsID2="" Max="88" />
  <HuiGuiDayZhiGou ID="102" HuoDongLevel="1" TotalYuanBao="0,-1" Day="6" Price="1|19|6876" GoodsID1="63202,1,1,0,0,0,0" GoodsID2="" Max="88" />
  <HuiGuiDayZhiGou ID="103" HuoDongLevel="1" TotalYuanBao="0,-1" Day="7" Price="1|11|6877" GoodsID1="2001,388,1,0,0,0,0|2002,388,1,0,0,0,0|2003,388,1,0,0,0,0|51419,18,0,0,0,0,0" GoodsID2="" Max="88" />
  <HuiGuiDayZhiGou ID="104" HuoDongLevel="1" TotalYuanBao="0,-1" Day="7" Price="1|11|6878" GoodsID1="2030,388,1,0,0,0,0|51419,18,0,0,0,0,0" GoodsID2="" Max="88" />
  <HuiGuiDayZhiGou ID="105" HuoDongLevel="1" TotalYuanBao="0,-1" Day="7" Price="1|2|6879" GoodsID1="2017,2888,1,0,0,0,0|2016,2388,1,0,0,0,0|51419,18,0,0,0,0,0" GoodsID2="" Max="88" />
  <HuiGuiDayZhiGou ID="106" HuoDongLevel="1" TotalYuanBao="0,-1" Day="7" Price="1|2|6880" GoodsID1="5050,2588,1,0,0,0,0|50305,18,1,0,0,0,0|50017,588,1,0,0,0,0|51419,18,0,0,0,0,0" GoodsID2="" Max="88" />
  <HuiGuiDayZhiGou ID="107" HuoDongLevel="1" TotalYuanBao="0,-1" Day="7" Price="1|14|6881" GoodsID1="2100,2588,1,0,0,0,0|5050,3888,1,0,0,0,0|5031,258,1,0,0,0,0|5041,258,1,0,0,0,0" GoodsID2="" Max="88" />
  <HuiGuiDayZhiGou ID="108" HuoDongLevel="1" TotalYuanBao="0,-1" Day="7" Price="1|16|6882" GoodsID1="7050,9888,1,0,0,0,0|50015,1588,1,0,0,0,0|5120,1088,1,0,0,0,0|51419,18,0,0,0,0,0" GoodsID2="" Max="88" />
  <HuiGuiDayZhiGou ID="109" HuoDongLevel="1" TotalYuanBao="0,-1" Day="7" Price="1|12|6883" GoodsID1="5120,628,1,0,0,0,0|7050,1888,1,0,0,0,0|51419,38,0,0,0,0,0" GoodsID2="" Max="88" />
  <HuiGuiDayZhiGou ID="110" HuoDongLevel="1" TotalYuanBao="0,-1" Day="7" Price="1|2|6884" GoodsID1="5312,108,1,0,0,0,0|7007,1688,1,0,0,0,0" GoodsID2="" Max="88" />
  <HuiGuiDayZhiGou ID="111" HuoDongLevel="1" TotalYuanBao="0,-1" Day="7" Price="1|14|6885" GoodsID1="63222,1,1,0,0,0,0|2103,688,1,0,0,0,0|2104,118,1,0,0,0,0" GoodsID2="" Max="88" />
  <HuiGuiDayZhiGou ID="112" HuoDongLevel="1" TotalYuanBao="0,-1" Day="7" Price="1|14|6886" GoodsID1="5331,100,1,0,0,0,0|5110,100,1,0,0,0,0|5220,100,1,0,0,0,0" GoodsID2="" Max="88" />
  <HuiGuiDayZhiGou ID="113" HuoDongLevel="1" TotalYuanBao="0,-1" Day="7" Price="1|16|6887" GoodsID1="5250,1688,1,0,0,0,0|2005,128,1,0,0,0,0" GoodsID2="" Max="88" />
  <HuiGuiDayZhiGou ID="114" HuoDongLevel="1" TotalYuanBao="0,-1" Day="7" Price="1|16|6888" GoodsID1="5284,288,1,0,0,0,0|5271,188,1,0,0,0,0" GoodsID2="" Max="88" />
  <HuiGuiDayZhiGou ID="115" HuoDongLevel="1" TotalYuanBao="0,-1" Day="7" Price="1|16|6889" GoodsID1="63215,1,1,0,0,0,0|51275,188,0,0,0,0,0" GoodsID2="" Max="88" />
  <HuiGuiDayZhiGou ID="116" HuoDongLevel="1" TotalYuanBao="0,-1" Day="7" Price="1|16|6890" GoodsID1="63201,1,1,0,0,0,0|51275,188,0,0,0,0,0" GoodsID2="" Max="88" />
  <HuiGuiDayZhiGou ID="117" HuoDongLevel="1" TotalYuanBao="0,-1" Day="7" Price="1|16|6891" GoodsID1="63203,1,1,0,0,0,0|51275,188,0,0,0,0,0" GoodsID2="" Max="88" />
  <HuiGuiDayZhiGou ID="118" HuoDongLevel="1" TotalYuanBao="0,-1" Day="7" Price="1|19|6892" GoodsID1="63216,1,1,0,0,0,0" GoodsID2="" Max="88" />
  <HuiGuiDayZhiGou ID="119" HuoDongLevel="1" TotalYuanBao="0,-1" Day="7" Price="1|19|6893" GoodsID1="63202,1,1,0,0,0,0" GoodsID2="" Max="88" />
  <HuiGuiDayZhiGou ID="120" HuoDongLevel="1" TotalYuanBao="0,-1" Day="8" Price="1|11|6894" GoodsID1="2001,388,1,0,0,0,0|2002,388,1,0,0,0,0|2003,388,1,0,0,0,0|51419,18,0,0,0,0,0" GoodsID2="" Max="88" />
  <HuiGuiDayZhiGou ID="121" HuoDongLevel="1" TotalYuanBao="0,-1" Day="8" Price="1|11|6895" GoodsID1="2030,388,1,0,0,0,0|51419,18,0,0,0,0,0" GoodsID2="" Max="88" />
  <HuiGuiDayZhiGou ID="122" HuoDongLevel="1" TotalYuanBao="0,-1" Day="8" Price="1|2|6896" GoodsID1="2017,2888,1,0,0,0,0|2016,2388,1,0,0,0,0|51419,18,0,0,0,0,0" GoodsID2="" Max="88" />
  <HuiGuiDayZhiGou ID="123" HuoDongLevel="1" TotalYuanBao="0,-1" Day="8" Price="1|2|6897" GoodsID1="5050,2588,1,0,0,0,0|50305,18,1,0,0,0,0|50017,588,1,0,0,0,0|51419,18,0,0,0,0,0" GoodsID2="" Max="88" />
  <HuiGuiDayZhiGou ID="124" HuoDongLevel="1" TotalYuanBao="0,-1" Day="8" Price="1|14|6898" GoodsID1="2100,2588,1,0,0,0,0|5050,3888,1,0,0,0,0|5031,258,1,0,0,0,0|5041,258,1,0,0,0,0" GoodsID2="" Max="88" />
  <HuiGuiDayZhiGou ID="125" HuoDongLevel="1" TotalYuanBao="0,-1" Day="8" Price="1|16|6899" GoodsID1="7050,9888,1,0,0,0,0|50015,1588,1,0,0,0,0|5120,1088,1,0,0,0,0|51419,18,0,0,0,0,0" GoodsID2="" Max="88" />
  <HuiGuiDayZhiGou ID="126" HuoDongLevel="1" TotalYuanBao="0,-1" Day="8" Price="1|12|6900" GoodsID1="5120,628,1,0,0,0,0|7050,1888,1,0,0,0,0|51419,38,0,0,0,0,0" GoodsID2="" Max="88" />
  <HuiGuiDayZhiGou ID="127" HuoDongLevel="1" TotalYuanBao="0,-1" Day="8" Price="1|2|6901" GoodsID1="5312,108,1,0,0,0,0|7007,1688,1,0,0,0,0" GoodsID2="" Max="88" />
  <HuiGuiDayZhiGou ID="128" HuoDongLevel="1" TotalYuanBao="0,-1" Day="8" Price="1|14|6902" GoodsID1="63222,1,1,0,0,0,0|2103,688,1,0,0,0,0|2104,118,1,0,0,0,0" GoodsID2="" Max="88" />
  <HuiGuiDayZhiGou ID="129" HuoDongLevel="1" TotalYuanBao="0,-1" Day="8" Price="1|14|6903" GoodsID1="5331,100,1,0,0,0,0|5110,100,1,0,0,0,0|5220,100,1,0,0,0,0" GoodsID2="" Max="88" />
  <HuiGuiDayZhiGou ID="130" HuoDongLevel="1" TotalYuanBao="0,-1" Day="8" Price="1|16|6904" GoodsID1="5250,1688,1,0,0,0,0|2005,128,1,0,0,0,0" GoodsID2="" Max="88" />
  <HuiGuiDayZhiGou ID="131" HuoDongLevel="1" TotalYuanBao="0,-1" Day="8" Price="1|16|6905" GoodsID1="5284,288,1,0,0,0,0|5271,188,1,0,0,0,0" GoodsID2="" Max="88" />
  <HuiGuiDayZhiGou ID="132" HuoDongLevel="1" TotalYuanBao="0,-1" Day="8" Price="1|16|6906" GoodsID1="63215,1,1,0,0,0,0|51275,188,0,0,0,0,0" GoodsID2="" Max="88" />
  <HuiGuiDayZhiGou ID="133" HuoDongLevel="1" TotalYuanBao="0,-1" Day="8" Price="1|16|6907" GoodsID1="63201,1,1,0,0,0,0|51275,188,0,0,0,0,0" GoodsID2="" Max="88" />
  <HuiGuiDayZhiGou ID="134" HuoDongLevel="1" TotalYuanBao="0,-1" Day="8" Price="1|16|6908" GoodsID1="63203,1,1,0,0,0,0|51275,188,0,0,0,0,0" GoodsID2="" Max="88" />
  <HuiGuiDayZhiGou ID="135" HuoDongLevel="1" TotalYuanBao="0,-1" Day="8" Price="1|19|6909" GoodsID1="63216,1,1,0,0,0,0" GoodsID2="" Max="88" />
  <HuiGuiDayZhiGou ID="136" HuoDongLevel="1" TotalYuanBao="0,-1" Day="8" Price="1|19|6910" GoodsID1="63202,1,1,0,0,0,0" GoodsID2="" Max="88" />
  <HuiGuiDayZhiGou ID="137" HuoDongLevel="2" TotalYuanBao="0,-1" Day="1" Price="1|11|7030" GoodsID1="2001,388,1,0,0,0,0|2002,388,1,0,0,0,0|2003,388,1,0,0,0,0|51419,18,0,0,0,0,0" GoodsID2="" Max="88" />
  <HuiGuiDayZhiGou ID="138" HuoDongLevel="2" TotalYuanBao="0,-1" Day="1" Price="1|11|7031" GoodsID1="2030,388,1,0,0,0,0|51419,18,0,0,0,0,0" GoodsID2="" Max="88" />
  <HuiGuiDayZhiGou ID="139" HuoDongLevel="2" TotalYuanBao="0,-1" Day="1" Price="1|2|7032" GoodsID1="2017,2888,1,0,0,0,0|2016,2388,1,0,0,0,0|51419,18,0,0,0,0,0" GoodsID2="" Max="88" />
  <HuiGuiDayZhiGou ID="140" HuoDongLevel="2" TotalYuanBao="0,-1" Day="1" Price="1|2|7033" GoodsID1="5050,2588,1,0,0,0,0|50305,18,1,0,0,0,0|50017,588,1,0,0,0,0|51419,18,0,0,0,0,0" GoodsID2="" Max="88" />
  <HuiGuiDayZhiGou ID="141" HuoDongLevel="2" TotalYuanBao="0,-1" Day="1" Price="1|14|7034" GoodsID1="2100,2588,1,0,0,0,0|5050,3888,1,0,0,0,0|5031,258,1,0,0,0,0|5041,258,1,0,0,0,0" GoodsID2="" Max="88" />
  <HuiGuiDayZhiGou ID="142" HuoDongLevel="2" TotalYuanBao="0,-1" Day="1" Price="1|16|7035" GoodsID1="7050,9888,1,0,0,0,0|50015,1588,1,0,0,0,0|5120,1088,1,0,0,0,0|51419,18,0,0,0,0,0" GoodsID2="" Max="88" />
  <HuiGuiDayZhiGou ID="143" HuoDongLevel="2" TotalYuanBao="0,-1" Day="1" Price="1|12|7036" GoodsID1="5120,628,1,0,0,0,0|7050,1888,1,0,0,0,0|51419,38,0,0,0,0,0" GoodsID2="" Max="88" />
  <HuiGuiDayZhiGou ID="144" HuoDongLevel="2" TotalYuanBao="0,-1" Day="1" Price="1|2|7037" GoodsID1="5312,108,1,0,0,0,0|7007,1688,1,0,0,0,0" GoodsID2="" Max="88" />
  <HuiGuiDayZhiGou ID="145" HuoDongLevel="2" TotalYuanBao="0,-1" Day="1" Price="1|14|7038" GoodsID1="63222,1,1,0,0,0,0|2103,688,1,0,0,0,0|2104,118,1,0,0,0,0" GoodsID2="" Max="88" />
  <HuiGuiDayZhiGou ID="146" HuoDongLevel="2" TotalYuanBao="0,-1" Day="1" Price="1|14|7039" GoodsID1="5331,100,1,0,0,0,0|5110,100,1,0,0,0,0|5220,100,1,0,0,0,0" GoodsID2="" Max="88" />
  <HuiGuiDayZhiGou ID="147" HuoDongLevel="2" TotalYuanBao="0,-1" Day="1" Price="1|16|7040" GoodsID1="5250,1688,1,0,0,0,0|2005,128,1,0,0,0,0" GoodsID2="" Max="88" />
  <HuiGuiDayZhiGou ID="148" HuoDongLevel="2" TotalYuanBao="0,-1" Day="1" Price="1|16|7041" GoodsID1="5284,288,1,0,0,0,0|5271,188,1,0,0,0,0" GoodsID2="" Max="88" />
  <HuiGuiDayZhiGou ID="149" HuoDongLevel="2" TotalYuanBao="0,-1" Day="1" Price="1|16|7042" GoodsID1="63215,1,1,0,0,0,0|51275,130,0,0,0,0,0" GoodsID2="" Max="88" />
  <HuiGuiDayZhiGou ID="150" HuoDongLevel="2" TotalYuanBao="0,-1" Day="1" Price="1|16|7043" GoodsID1="63201,1,1,0,0,0,0|51275,130,0,0,0,0,0" GoodsID2="" Max="88" />
  <HuiGuiDayZhiGou ID="151" HuoDongLevel="2" TotalYuanBao="0,-1" Day="1" Price="1|16|7044" GoodsID1="63203,1,1,0,0,0,0|51275,130,0,0,0,0,0" GoodsID2="" Max="88" />
  <HuiGuiDayZhiGou ID="152" HuoDongLevel="2" TotalYuanBao="0,-1" Day="1" Price="1|19|7045" GoodsID1="63216,1,1,0,0,0,0" GoodsID2="" Max="88" />
  <HuiGuiDayZhiGou ID="153" HuoDongLevel="2" TotalYuanBao="0,-1" Day="1" Price="1|19|7046" GoodsID1="63202,1,1,0,0,0,0" GoodsID2="" Max="88" />
  <HuiGuiDayZhiGou ID="154" HuoDongLevel="2" TotalYuanBao="0,-1" Day="2" Price="1|11|7047" GoodsID1="2001,388,1,0,0,0,0|2002,388,1,0,0,0,0|2003,388,1,0,0,0,0|51419,18,0,0,0,0,0" GoodsID2="" Max="88" />
  <HuiGuiDayZhiGou ID="155" HuoDongLevel="2" TotalYuanBao="0,-1" Day="2" Price="1|11|7048" GoodsID1="2030,388,1,0,0,0,0|51419,18,0,0,0,0,0" GoodsID2="" Max="88" />
  <HuiGuiDayZhiGou ID="156" HuoDongLevel="2" TotalYuanBao="0,-1" Day="2" Price="1|2|7049" GoodsID1="2017,2888,1,0,0,0,0|2016,2388,1,0,0,0,0|51419,18,0,0,0,0,0" GoodsID2="" Max="88" />
  <HuiGuiDayZhiGou ID="157" HuoDongLevel="2" TotalYuanBao="0,-1" Day="2" Price="1|2|7050" GoodsID1="5050,2588,1,0,0,0,0|50305,18,1,0,0,0,0|50017,588,1,0,0,0,0|51419,18,0,0,0,0,0" GoodsID2="" Max="88" />
  <HuiGuiDayZhiGou ID="158" HuoDongLevel="2" TotalYuanBao="0,-1" Day="2" Price="1|14|7051" GoodsID1="2100,2588,1,0,0,0,0|5050,3888,1,0,0,0,0|5031,258,1,0,0,0,0|5041,258,1,0,0,0,0" GoodsID2="" Max="88" />
  <HuiGuiDayZhiGou ID="159" HuoDongLevel="2" TotalYuanBao="0,-1" Day="2" Price="1|16|7052" GoodsID1="7050,9888,1,0,0,0,0|50015,1588,1,0,0,0,0|5120,1088,1,0,0,0,0|51419,18,0,0,0,0,0" GoodsID2="" Max="88" />
  <HuiGuiDayZhiGou ID="160" HuoDongLevel="2" TotalYuanBao="0,-1" Day="2" Price="1|12|7053" GoodsID1="5120,628,1,0,0,0,0|7050,1888,1,0,0,0,0|51419,38,0,0,0,0,0" GoodsID2="" Max="88" />
  <HuiGuiDayZhiGou ID="161" HuoDongLevel="2" TotalYuanBao="0,-1" Day="2" Price="1|2|7054" GoodsID1="5312,108,1,0,0,0,0|7007,1688,1,0,0,0,0" GoodsID2="" Max="88" />
  <HuiGuiDayZhiGou ID="162" HuoDongLevel="2" TotalYuanBao="0,-1" Day="2" Price="1|14|7055" GoodsID1="63222,1,1,0,0,0,0|2103,688,1,0,0,0,0|2104,118,1,0,0,0,0" GoodsID2="" Max="88" />
  <HuiGuiDayZhiGou ID="163" HuoDongLevel="2" TotalYuanBao="0,-1" Day="2" Price="1|14|7056" GoodsID1="5331,100,1,0,0,0,0|5110,100,1,0,0,0,0|5220,100,1,0,0,0,0" GoodsID2="" Max="88" />
  <HuiGuiDayZhiGou ID="164" HuoDongLevel="2" TotalYuanBao="0,-1" Day="2" Price="1|16|7057" GoodsID1="5250,1688,1,0,0,0,0|2005,128,1,0,0,0,0" GoodsID2="" Max="88" />
  <HuiGuiDayZhiGou ID="165" HuoDongLevel="2" TotalYuanBao="0,-1" Day="2" Price="1|16|7058" GoodsID1="5284,288,1,0,0,0,0|5271,188,1,0,0,0,0" GoodsID2="" Max="88" />
  <HuiGuiDayZhiGou ID="166" HuoDongLevel="2" TotalYuanBao="0,-1" Day="2" Price="1|16|7059" GoodsID1="63215,1,1,0,0,0,0|51275,130,0,0,0,0,0" GoodsID2="" Max="88" />
  <HuiGuiDayZhiGou ID="167" HuoDongLevel="2" TotalYuanBao="0,-1" Day="2" Price="1|16|7060" GoodsID1="63201,1,1,0,0,0,0|51275,130,0,0,0,0,0" GoodsID2="" Max="88" />
  <HuiGuiDayZhiGou ID="168" HuoDongLevel="2" TotalYuanBao="0,-1" Day="2" Price="1|16|7061" GoodsID1="63203,1,1,0,0,0,0|51275,130,0,0,0,0,0" GoodsID2="" Max="88" />
  <HuiGuiDayZhiGou ID="169" HuoDongLevel="2" TotalYuanBao="0,-1" Day="2" Price="1|19|7062" GoodsID1="63216,1,1,0,0,0,0" GoodsID2="" Max="88" />
  <HuiGuiDayZhiGou ID="170" HuoDongLevel="2" TotalYuanBao="0,-1" Day="2" Price="1|19|7063" GoodsID1="63202,1,1,0,0,0,0" GoodsID2="" Max="88" />
  <HuiGuiDayZhiGou ID="171" HuoDongLevel="2" TotalYuanBao="0,-1" Day="3" Price="1|11|7064" GoodsID1="2001,388,1,0,0,0,0|2002,388,1,0,0,0,0|2003,388,1,0,0,0,0|51419,18,0,0,0,0,0" GoodsID2="" Max="88" />
  <HuiGuiDayZhiGou ID="172" HuoDongLevel="2" TotalYuanBao="0,-1" Day="3" Price="1|11|7065" GoodsID1="2030,388,1,0,0,0,0|51419,18,0,0,0,0,0" GoodsID2="" Max="88" />
  <HuiGuiDayZhiGou ID="173" HuoDongLevel="2" TotalYuanBao="0,-1" Day="3" Price="1|2|7066" GoodsID1="2017,2888,1,0,0,0,0|2016,2388,1,0,0,0,0|51419,18,0,0,0,0,0" GoodsID2="" Max="88" />
  <HuiGuiDayZhiGou ID="174" HuoDongLevel="2" TotalYuanBao="0,-1" Day="3" Price="1|2|7067" GoodsID1="5050,2588,1,0,0,0,0|50305,18,1,0,0,0,0|50017,588,1,0,0,0,0|51419,18,0,0,0,0,0" GoodsID2="" Max="88" />
  <HuiGuiDayZhiGou ID="175" HuoDongLevel="2" TotalYuanBao="0,-1" Day="3" Price="1|14|7068" GoodsID1="2100,2588,1,0,0,0,0|5050,3888,1,0,0,0,0|5031,258,1,0,0,0,0|5041,258,1,0,0,0,0" GoodsID2="" Max="88" />
  <HuiGuiDayZhiGou ID="176" HuoDongLevel="2" TotalYuanBao="0,-1" Day="3" Price="1|16|7069" GoodsID1="7050,9888,1,0,0,0,0|50015,1588,1,0,0,0,0|5120,1088,1,0,0,0,0|51419,18,0,0,0,0,0" GoodsID2="" Max="88" />
  <HuiGuiDayZhiGou ID="177" HuoDongLevel="2" TotalYuanBao="0,-1" Day="3" Price="1|12|7070" GoodsID1="5120,628,1,0,0,0,0|7050,1888,1,0,0,0,0|51419,38,0,0,0,0,0" GoodsID2="" Max="88" />
  <HuiGuiDayZhiGou ID="178" HuoDongLevel="2" TotalYuanBao="0,-1" Day="3" Price="1|2|7071" GoodsID1="5312,108,1,0,0,0,0|7007,1688,1,0,0,0,0" GoodsID2="" Max="88" />
  <HuiGuiDayZhiGou ID="179" HuoDongLevel="2" TotalYuanBao="0,-1" Day="3" Price="1|14|7072" GoodsID1="63222,1,1,0,0,0,0|2103,688,1,0,0,0,0|2104,118,1,0,0,0,0" GoodsID2="" Max="88" />
  <HuiGuiDayZhiGou ID="180" HuoDongLevel="2" TotalYuanBao="0,-1" Day="3" Price="1|14|7073" GoodsID1="5331,100,1,0,0,0,0|5110,100,1,0,0,0,0|5220,100,1,0,0,0,0" GoodsID2="" Max="88" />
  <HuiGuiDayZhiGou ID="181" HuoDongLevel="2" TotalYuanBao="0,-1" Day="3" Price="1|16|7074" GoodsID1="5250,1688,1,0,0,0,0|2005,128,1,0,0,0,0" GoodsID2="" Max="88" />
  <HuiGuiDayZhiGou ID="182" HuoDongLevel="2" TotalYuanBao="0,-1" Day="3" Price="1|16|7075" GoodsID1="5284,288,1,0,0,0,0|5271,188,1,0,0,0,0" GoodsID2="" Max="88" />
  <HuiGuiDayZhiGou ID="183" HuoDongLevel="2" TotalYuanBao="0,-1" Day="3" Price="1|16|7076" GoodsID1="63215,1,1,0,0,0,0|51275,130,0,0,0,0,0" GoodsID2="" Max="88" />
  <HuiGuiDayZhiGou ID="184" HuoDongLevel="2" TotalYuanBao="0,-1" Day="3" Price="1|16|7077" GoodsID1="63201,1,1,0,0,0,0|51275,130,0,0,0,0,0" GoodsID2="" Max="88" />
  <HuiGuiDayZhiGou ID="185" HuoDongLevel="2" TotalYuanBao="0,-1" Day="3" Price="1|16|7078" GoodsID1="63203,1,1,0,0,0,0|51275,130,0,0,0,0,0" GoodsID2="" Max="88" />
  <HuiGuiDayZhiGou ID="186" HuoDongLevel="2" TotalYuanBao="0,-1" Day="3" Price="1|19|7079" GoodsID1="63216,1,1,0,0,0,0" GoodsID2="" Max="88" />
  <HuiGuiDayZhiGou ID="187" HuoDongLevel="2" TotalYuanBao="0,-1" Day="3" Price="1|19|7080" GoodsID1="63202,1,1,0,0,0,0" GoodsID2="" Max="88" />
  <HuiGuiDayZhiGou ID="188" HuoDongLevel="2" TotalYuanBao="0,-1" Day="4" Price="1|11|7081" GoodsID1="2001,388,1,0,0,0,0|2002,388,1,0,0,0,0|2003,388,1,0,0,0,0|51419,18,0,0,0,0,0" GoodsID2="" Max="88" />
  <HuiGuiDayZhiGou ID="189" HuoDongLevel="2" TotalYuanBao="0,-1" Day="4" Price="1|11|7082" GoodsID1="2030,388,1,0,0,0,0|51419,18,0,0,0,0,0" GoodsID2="" Max="88" />
  <HuiGuiDayZhiGou ID="190" HuoDongLevel="2" TotalYuanBao="0,-1" Day="4" Price="1|2|7083" GoodsID1="2017,2888,1,0,0,0,0|2016,2388,1,0,0,0,0|51419,18,0,0,0,0,0" GoodsID2="" Max="88" />
  <HuiGuiDayZhiGou ID="191" HuoDongLevel="2" TotalYuanBao="0,-1" Day="4" Price="1|2|7084" GoodsID1="5050,2588,1,0,0,0,0|50305,18,1,0,0,0,0|50017,588,1,0,0,0,0|51419,18,0,0,0,0,0" GoodsID2="" Max="88" />
  <HuiGuiDayZhiGou ID="192" HuoDongLevel="2" TotalYuanBao="0,-1" Day="4" Price="1|14|7085" GoodsID1="2100,2588,1,0,0,0,0|5050,3888,1,0,0,0,0|5031,258,1,0,0,0,0|5041,258,1,0,0,0,0" GoodsID2="" Max="88" />
  <HuiGuiDayZhiGou ID="193" HuoDongLevel="2" TotalYuanBao="0,-1" Day="4" Price="1|16|7086" GoodsID1="7050,9888,1,0,0,0,0|50015,1588,1,0,0,0,0|5120,1088,1,0,0,0,0|51419,18,0,0,0,0,0" GoodsID2="" Max="88" />
  <HuiGuiDayZhiGou ID="194" HuoDongLevel="2" TotalYuanBao="0,-1" Day="4" Price="1|12|7087" GoodsID1="5120,628,1,0,0,0,0|7050,1888,1,0,0,0,0|51419,38,0,0,0,0,0" GoodsID2="" Max="88" />
  <HuiGuiDayZhiGou ID="195" HuoDongLevel="2" TotalYuanBao="0,-1" Day="4" Price="1|2|7088" GoodsID1="5312,108,1,0,0,0,0|7007,1688,1,0,0,0,0" GoodsID2="" Max="88" />
  <HuiGuiDayZhiGou ID="196" HuoDongLevel="2" TotalYuanBao="0,-1" Day="4" Price="1|14|7089" GoodsID1="63222,1,1,0,0,0,0|2103,688,1,0,0,0,0|2104,118,1,0,0,0,0" GoodsID2="" Max="88" />
  <HuiGuiDayZhiGou ID="197" HuoDongLevel="2" TotalYuanBao="0,-1" Day="4" Price="1|14|7090" GoodsID1="5331,100,1,0,0,0,0|5110,100,1,0,0,0,0|5220,100,1,0,0,0,0" GoodsID2="" Max="88" />
  <HuiGuiDayZhiGou ID="198" HuoDongLevel="2" TotalYuanBao="0,-1" Day="4" Price="1|16|7091" GoodsID1="5250,1688,1,0,0,0,0|2005,128,1,0,0,0,0" GoodsID2="" Max="88" />
  <HuiGuiDayZhiGou ID="199" HuoDongLevel="2" TotalYuanBao="0,-1" Day="4" Price="1|16|7092" GoodsID1="5284,288,1,0,0,0,0|5271,188,1,0,0,0,0" GoodsID2="" Max="88" />
  <HuiGuiDayZhiGou ID="200" HuoDongLevel="2" TotalYuanBao="0,-1" Day="4" Price="1|16|7093" GoodsID1="63215,1,1,0,0,0,0|51275,130,0,0,0,0,0" GoodsID2="" Max="88" />
  <HuiGuiDayZhiGou ID="201" HuoDongLevel="2" TotalYuanBao="0,-1" Day="4" Price="1|16|7094" GoodsID1="63201,1,1,0,0,0,0|51275,130,0,0,0,0,0" GoodsID2="" Max="88" />
  <HuiGuiDayZhiGou ID="202" HuoDongLevel="2" TotalYuanBao="0,-1" Day="4" Price="1|16|7095" GoodsID1="63203,1,1,0,0,0,0|51275,130,0,0,0,0,0" GoodsID2="" Max="88" />
  <HuiGuiDayZhiGou ID="203" HuoDongLevel="2" TotalYuanBao="0,-1" Day="4" Price="1|19|7096" GoodsID1="63216,1,1,0,0,0,0" GoodsID2="" Max="88" />
  <HuiGuiDayZhiGou ID="204" HuoDongLevel="2" TotalYuanBao="0,-1" Day="4" Price="1|19|7097" GoodsID1="63202,1,1,0,0,0,0" GoodsID2="" Max="88" />
  <HuiGuiDayZhiGou ID="205" HuoDongLevel="2" TotalYuanBao="0,-1" Day="5" Price="1|11|7098" GoodsID1="2001,388,1,0,0,0,0|2002,388,1,0,0,0,0|2003,388,1,0,0,0,0|51419,18,0,0,0,0,0" GoodsID2="" Max="88" />
  <HuiGuiDayZhiGou ID="206" HuoDongLevel="2" TotalYuanBao="0,-1" Day="5" Price="1|11|7099" GoodsID1="2030,388,1,0,0,0,0|51419,18,0,0,0,0,0" GoodsID2="" Max="88" />
  <HuiGuiDayZhiGou ID="207" HuoDongLevel="2" TotalYuanBao="0,-1" Day="5" Price="1|2|7100" GoodsID1="2017,2888,1,0,0,0,0|2016,2388,1,0,0,0,0|51419,18,0,0,0,0,0" GoodsID2="" Max="88" />
  <HuiGuiDayZhiGou ID="208" HuoDongLevel="2" TotalYuanBao="0,-1" Day="5" Price="1|2|7101" GoodsID1="5050,2588,1,0,0,0,0|50305,18,1,0,0,0,0|50017,588,1,0,0,0,0|51419,18,0,0,0,0,0" GoodsID2="" Max="88" />
  <HuiGuiDayZhiGou ID="209" HuoDongLevel="2" TotalYuanBao="0,-1" Day="5" Price="1|14|7102" GoodsID1="2100,2588,1,0,0,0,0|5050,3888,1,0,0,0,0|5031,258,1,0,0,0,0|5041,258,1,0,0,0,0" GoodsID2="" Max="88" />
  <HuiGuiDayZhiGou ID="210" HuoDongLevel="2" TotalYuanBao="0,-1" Day="5" Price="1|16|7103" GoodsID1="7050,9888,1,0,0,0,0|50015,1588,1,0,0,0,0|5120,1088,1,0,0,0,0|51419,18,0,0,0,0,0" GoodsID2="" Max="88" />
  <HuiGuiDayZhiGou ID="211" HuoDongLevel="2" TotalYuanBao="0,-1" Day="5" Price="1|12|7104" GoodsID1="5120,628,1,0,0,0,0|7050,1888,1,0,0,0,0|51419,38,0,0,0,0,0" GoodsID2="" Max="88" />
  <HuiGuiDayZhiGou ID="212" HuoDongLevel="2" TotalYuanBao="0,-1" Day="5" Price="1|2|7105" GoodsID1="5312,108,1,0,0,0,0|7007,1688,1,0,0,0,0" GoodsID2="" Max="88" />
  <HuiGuiDayZhiGou ID="213" HuoDongLevel="2" TotalYuanBao="0,-1" Day="5" Price="1|14|7106" GoodsID1="63222,1,1,0,0,0,0|2103,688,1,0,0,0,0|2104,118,1,0,0,0,0" GoodsID2="" Max="88" />
  <HuiGuiDayZhiGou ID="214" HuoDongLevel="2" TotalYuanBao="0,-1" Day="5" Price="1|14|7107" GoodsID1="5331,100,1,0,0,0,0|5110,100,1,0,0,0,0|5220,100,1,0,0,0,0" GoodsID2="" Max="88" />
  <HuiGuiDayZhiGou ID="215" HuoDongLevel="2" TotalYuanBao="0,-1" Day="5" Price="1|16|7108" GoodsID1="5250,1688,1,0,0,0,0|2005,128,1,0,0,0,0" GoodsID2="" Max="88" />
  <HuiGuiDayZhiGou ID="216" HuoDongLevel="2" TotalYuanBao="0,-1" Day="5" Price="1|16|7109" GoodsID1="5284,288,1,0,0,0,0|5271,188,1,0,0,0,0" GoodsID2="" Max="88" />
  <HuiGuiDayZhiGou ID="217" HuoDongLevel="2" TotalYuanBao="0,-1" Day="5" Price="1|16|7110" GoodsID1="63215,1,1,0,0,0,0|51275,130,0,0,0,0,0" GoodsID2="" Max="88" />
  <HuiGuiDayZhiGou ID="218" HuoDongLevel="2" TotalYuanBao="0,-1" Day="5" Price="1|16|7111" GoodsID1="63201,1,1,0,0,0,0|51275,130,0,0,0,0,0" GoodsID2="" Max="88" />
  <HuiGuiDayZhiGou ID="219" HuoDongLevel="2" TotalYuanBao="0,-1" Day="5" Price="1|16|7112" GoodsID1="63203,1,1,0,0,0,0|51275,130,0,0,0,0,0" GoodsID2="" Max="88" />
  <HuiGuiDayZhiGou ID="220" HuoDongLevel="2" TotalYuanBao="0,-1" Day="5" Price="1|19|7113" GoodsID1="63216,1,1,0,0,0,0" GoodsID2="" Max="88" />
  <HuiGuiDayZhiGou ID="221" HuoDongLevel="2" TotalYuanBao="0,-1" Day="5" Price="1|19|7114" GoodsID1="63202,1,1,0,0,0,0" GoodsID2="" Max="88" />
  <HuiGuiDayZhiGou ID="222" HuoDongLevel="2" TotalYuanBao="0,-1" Day="6" Price="1|11|7115" GoodsID1="2001,388,1,0,0,0,0|2002,388,1,0,0,0,0|2003,388,1,0,0,0,0|51419,18,0,0,0,0,0" GoodsID2="" Max="88" />
  <HuiGuiDayZhiGou ID="223" HuoDongLevel="2" TotalYuanBao="0,-1" Day="6" Price="1|11|7116" GoodsID1="2030,388,1,0,0,0,0|51419,18,0,0,0,0,0" GoodsID2="" Max="88" />
  <HuiGuiDayZhiGou ID="224" HuoDongLevel="2" TotalYuanBao="0,-1" Day="6" Price="1|2|7117" GoodsID1="2017,2888,1,0,0,0,0|2016,2388,1,0,0,0,0|51419,18,0,0,0,0,0" GoodsID2="" Max="88" />
  <HuiGuiDayZhiGou ID="225" HuoDongLevel="2" TotalYuanBao="0,-1" Day="6" Price="1|2|7118" GoodsID1="5050,2588,1,0,0,0,0|50305,18,1,0,0,0,0|50017,588,1,0,0,0,0|51419,18,0,0,0,0,0" GoodsID2="" Max="88" />
  <HuiGuiDayZhiGou ID="226" HuoDongLevel="2" TotalYuanBao="0,-1" Day="6" Price="1|14|7119" GoodsID1="2100,2588,1,0,0,0,0|5050,3888,1,0,0,0,0|5031,258,1,0,0,0,0|5041,258,1,0,0,0,0" GoodsID2="" Max="88" />
  <HuiGuiDayZhiGou ID="227" HuoDongLevel="2" TotalYuanBao="0,-1" Day="6" Price="1|16|7120" GoodsID1="7050,9888,1,0,0,0,0|50015,1588,1,0,0,0,0|5120,1088,1,0,0,0,0|51419,18,0,0,0,0,0" GoodsID2="" Max="88" />
  <HuiGuiDayZhiGou ID="228" HuoDongLevel="2" TotalYuanBao="0,-1" Day="6" Price="1|12|7121" GoodsID1="5120,628,1,0,0,0,0|7050,1888,1,0,0,0,0|51419,38,0,0,0,0,0" GoodsID2="" Max="88" />
  <HuiGuiDayZhiGou ID="229" HuoDongLevel="2" TotalYuanBao="0,-1" Day="6" Price="1|2|7122" GoodsID1="5312,108,1,0,0,0,0|7007,1688,1,0,0,0,0" GoodsID2="" Max="88" />
  <HuiGuiDayZhiGou ID="230" HuoDongLevel="2" TotalYuanBao="0,-1" Day="6" Price="1|14|7123" GoodsID1="63222,1,1,0,0,0,0|2103,688,1,0,0,0,0|2104,118,1,0,0,0,0" GoodsID2="" Max="88" />
  <HuiGuiDayZhiGou ID="231" HuoDongLevel="2" TotalYuanBao="0,-1" Day="6" Price="1|14|7124" GoodsID1="5331,100,1,0,0,0,0|5110,100,1,0,0,0,0|5220,100,1,0,0,0,0" GoodsID2="" Max="88" />
  <HuiGuiDayZhiGou ID="232" HuoDongLevel="2" TotalYuanBao="0,-1" Day="6" Price="1|16|7125" GoodsID1="5250,1688,1,0,0,0,0|2005,128,1,0,0,0,0" GoodsID2="" Max="88" />
  <HuiGuiDayZhiGou ID="233" HuoDongLevel="2" TotalYuanBao="0,-1" Day="6" Price="1|16|7126" GoodsID1="5284,288,1,0,0,0,0|5271,188,1,0,0,0,0" GoodsID2="" Max="88" />
  <HuiGuiDayZhiGou ID="234" HuoDongLevel="2" TotalYuanBao="0,-1" Day="6" Price="1|16|7127" GoodsID1="63215,1,1,0,0,0,0|51275,130,0,0,0,0,0" GoodsID2="" Max="88" />
  <HuiGuiDayZhiGou ID="235" HuoDongLevel="2" TotalYuanBao="0,-1" Day="6" Price="1|16|7128" GoodsID1="63201,1,1,0,0,0,0|51275,130,0,0,0,0,0" GoodsID2="" Max="88" />
  <HuiGuiDayZhiGou ID="236" HuoDongLevel="2" TotalYuanBao="0,-1" Day="6" Price="1|16|7129" GoodsID1="63203,1,1,0,0,0,0|51275,130,0,0,0,0,0" GoodsID2="" Max="88" />
  <HuiGuiDayZhiGou ID="237" HuoDongLevel="2" TotalYuanBao="0,-1" Day="6" Price="1|19|7130" GoodsID1="63216,1,1,0,0,0,0" GoodsID2="" Max="88" />
  <HuiGuiDayZhiGou ID="238" HuoDongLevel="2" TotalYuanBao="0,-1" Day="6" Price="1|19|7131" GoodsID1="63202,1,1,0,0,0,0" GoodsID2="" Max="88" />
  <HuiGuiDayZhiGou ID="239" HuoDongLevel="2" TotalYuanBao="0,-1" Day="7" Price="1|11|7132" GoodsID1="2001,388,1,0,0,0,0|2002,388,1,0,0,0,0|2003,388,1,0,0,0,0|51419,18,0,0,0,0,0" GoodsID2="" Max="88" />
  <HuiGuiDayZhiGou ID="240" HuoDongLevel="2" TotalYuanBao="0,-1" Day="7" Price="1|11|7133" GoodsID1="2030,388,1,0,0,0,0|51419,18,0,0,0,0,0" GoodsID2="" Max="88" />
  <HuiGuiDayZhiGou ID="241" HuoDongLevel="2" TotalYuanBao="0,-1" Day="7" Price="1|2|7134" GoodsID1="2017,2888,1,0,0,0,0|2016,2388,1,0,0,0,0|51419,18,0,0,0,0,0" GoodsID2="" Max="88" />
  <HuiGuiDayZhiGou ID="242" HuoDongLevel="2" TotalYuanBao="0,-1" Day="7" Price="1|2|7135" GoodsID1="5050,2588,1,0,0,0,0|50305,18,1,0,0,0,0|50017,588,1,0,0,0,0|51419,18,0,0,0,0,0" GoodsID2="" Max="88" />
  <HuiGuiDayZhiGou ID="243" HuoDongLevel="2" TotalYuanBao="0,-1" Day="7" Price="1|14|7136" GoodsID1="2100,2588,1,0,0,0,0|5050,3888,1,0,0,0,0|5031,258,1,0,0,0,0|5041,258,1,0,0,0,0" GoodsID2="" Max="88" />
  <HuiGuiDayZhiGou ID="244" HuoDongLevel="2" TotalYuanBao="0,-1" Day="7" Price="1|16|7137" GoodsID1="7050,9888,1,0,0,0,0|50015,1588,1,0,0,0,0|5120,1088,1,0,0,0,0|51419,18,0,0,0,0,0" GoodsID2="" Max="88" />
  <HuiGuiDayZhiGou ID="245" HuoDongLevel="2" TotalYuanBao="0,-1" Day="7" Price="1|12|7138" GoodsID1="5120,628,1,0,0,0,0|7050,1888,1,0,0,0,0|51419,38,0,0,0,0,0" GoodsID2="" Max="88" />
  <HuiGuiDayZhiGou ID="246" HuoDongLevel="2" TotalYuanBao="0,-1" Day="7" Price="1|2|7139" GoodsID1="5312,108,1,0,0,0,0|7007,1688,1,0,0,0,0" GoodsID2="" Max="88" />
  <HuiGuiDayZhiGou ID="247" HuoDongLevel="2" TotalYuanBao="0,-1" Day="7" Price="1|14|7140" GoodsID1="63222,1,1,0,0,0,0|2103,688,1,0,0,0,0|2104,118,1,0,0,0,0" GoodsID2="" Max="88" />
  <HuiGuiDayZhiGou ID="248" HuoDongLevel="2" TotalYuanBao="0,-1" Day="7" Price="1|14|7141" GoodsID1="5331,100,1,0,0,0,0|5110,100,1,0,0,0,0|5220,100,1,0,0,0,0" GoodsID2="" Max="88" />
  <HuiGuiDayZhiGou ID="249" HuoDongLevel="2" TotalYuanBao="0,-1" Day="7" Price="1|16|7142" GoodsID1="5250,1688,1,0,0,0,0|2005,128,1,0,0,0,0" GoodsID2="" Max="88" />
  <HuiGuiDayZhiGou ID="250" HuoDongLevel="2" TotalYuanBao="0,-1" Day="7" Price="1|16|7143" GoodsID1="5284,288,1,0,0,0,0|5271,188,1,0,0,0,0" GoodsID2="" Max="88" />
  <HuiGuiDayZhiGou ID="251" HuoDongLevel="2" TotalYuanBao="0,-1" Day="7" Price="1|16|7144" GoodsID1="63215,1,1,0,0,0,0|51275,130,0,0,0,0,0" GoodsID2="" Max="88" />
  <HuiGuiDayZhiGou ID="252" HuoDongLevel="2" TotalYuanBao="0,-1" Day="7" Price="1|16|7145" GoodsID1="63201,1,1,0,0,0,0|51275,130,0,0,0,0,0" GoodsID2="" Max="88" />
  <HuiGuiDayZhiGou ID="253" HuoDongLevel="2" TotalYuanBao="0,-1" Day="7" Price="1|16|7146" GoodsID1="63203,1,1,0,0,0,0|51275,130,0,0,0,0,0" GoodsID2="" Max="88" />
  <HuiGuiDayZhiGou ID="254" HuoDongLevel="2" TotalYuanBao="0,-1" Day="7" Price="1|19|7147" GoodsID1="63216,1,1,0,0,0,0" GoodsID2="" Max="88" />
  <HuiGuiDayZhiGou ID="255" HuoDongLevel="2" TotalYuanBao="0,-1" Day="7" Price="1|19|7148" GoodsID1="63202,1,1,0,0,0,0" GoodsID2="" Max="88" />
  <HuiGuiDayZhiGou ID="256" HuoDongLevel="2" TotalYuanBao="0,-1" Day="8" Price="1|11|7149" GoodsID1="2001,388,1,0,0,0,0|2002,388,1,0,0,0,0|2003,388,1,0,0,0,0|51419,18,0,0,0,0,0" GoodsID2="" Max="88" />
  <HuiGuiDayZhiGou ID="257" HuoDongLevel="2" TotalYuanBao="0,-1" Day="8" Price="1|11|7150" GoodsID1="2030,388,1,0,0,0,0|51419,18,0,0,0,0,0" GoodsID2="" Max="88" />
  <HuiGuiDayZhiGou ID="258" HuoDongLevel="2" TotalYuanBao="0,-1" Day="8" Price="1|2|7151" GoodsID1="2017,2888,1,0,0,0,0|2016,2388,1,0,0,0,0|51419,18,0,0,0,0,0" GoodsID2="" Max="88" />
  <HuiGuiDayZhiGou ID="259" HuoDongLevel="2" TotalYuanBao="0,-1" Day="8" Price="1|2|7152" GoodsID1="5050,2588,1,0,0,0,0|50305,18,1,0,0,0,0|50017,588,1,0,0,0,0|51419,18,0,0,0,0,0" GoodsID2="" Max="88" />
  <HuiGuiDayZhiGou ID="260" HuoDongLevel="2" TotalYuanBao="0,-1" Day="8" Price="1|14|7153" GoodsID1="2100,2588,1,0,0,0,0|5050,3888,1,0,0,0,0|5031,258,1,0,0,0,0|5041,258,1,0,0,0,0" GoodsID2="" Max="88" />
  <HuiGuiDayZhiGou ID="261" HuoDongLevel="2" TotalYuanBao="0,-1" Day="8" Price="1|16|7154" GoodsID1="7050,9888,1,0,0,0,0|50015,1588,1,0,0,0,0|5120,1088,1,0,0,0,0|51419,18,0,0,0,0,0" GoodsID2="" Max="88" />
  <HuiGuiDayZhiGou ID="262" HuoDongLevel="2" TotalYuanBao="0,-1" Day="8" Price="1|12|7155" GoodsID1="5120,628,1,0,0,0,0|7050,1888,1,0,0,0,0|51419,38,0,0,0,0,0" GoodsID2="" Max="88" />
  <HuiGuiDayZhiGou ID="263" HuoDongLevel="2" TotalYuanBao="0,-1" Day="8" Price="1|2|7156" GoodsID1="5312,108,1,0,0,0,0|7007,1688,1,0,0,0,0" GoodsID2="" Max="88" />
  <HuiGuiDayZhiGou ID="264" HuoDongLevel="2" TotalYuanBao="0,-1" Day="8" Price="1|14|7157" GoodsID1="63222,1,1,0,0,0,0|2103,688,1,0,0,0,0|2104,118,1,0,0,0,0" GoodsID2="" Max="88" />
  <HuiGuiDayZhiGou ID="265" HuoDongLevel="2" TotalYuanBao="0,-1" Day="8" Price="1|14|7158" GoodsID1="5331,100,1,0,0,0,0|5110,100,1,0,0,0,0|5220,100,1,0,0,0,0" GoodsID2="" Max="88" />
  <HuiGuiDayZhiGou ID="266" HuoDongLevel="2" TotalYuanBao="0,-1" Day="8" Price="1|16|7159" GoodsID1="5250,1688,1,0,0,0,0|2005,128,1,0,0,0,0" GoodsID2="" Max="88" />
  <HuiGuiDayZhiGou ID="267" HuoDongLevel="2" TotalYuanBao="0,-1" Day="8" Price="1|16|7160" GoodsID1="5284,288,1,0,0,0,0|5271,188,1,0,0,0,0" GoodsID2="" Max="88" />
  <HuiGuiDayZhiGou ID="268" HuoDongLevel="2" TotalYuanBao="0,-1" Day="8" Price="1|16|7161" GoodsID1="63215,1,1,0,0,0,0|51275,130,0,0,0,0,0" GoodsID2="" Max="88" />
  <HuiGuiDayZhiGou ID="269" HuoDongLevel="2" TotalYuanBao="0,-1" Day="8" Price="1|16|7162" GoodsID1="63201,1,1,0,0,0,0|51275,130,0,0,0,0,0" GoodsID2="" Max="88" />
  <HuiGuiDayZhiGou ID="270" HuoDongLevel="2" TotalYuanBao="0,-1" Day="8" Price="1|16|7163" GoodsID1="63203,1,1,0,0,0,0|51275,130,0,0,0,0,0" GoodsID2="" Max="88" />
  <HuiGuiDayZhiGou ID="271" HuoDongLevel="2" TotalYuanBao="0,-1" Day="8" Price="1|19|7164" GoodsID1="63216,1,1,0,0,0,0" GoodsID2="" Max="88" />
  <HuiGuiDayZhiGou ID="272" HuoDongLevel="2" TotalYuanBao="0,-1" Day="8" Price="1|19|7165" GoodsID1="63202,1,1,0,0,0,0" GoodsID2="" Max="88" />
  <HuiGuiDayZhiGou ID="273" HuoDongLevel="3" TotalYuanBao="0,-1" Day="1" Price="1|11|7285" GoodsID1="2001,388,1,0,0,0,0|2002,388,1,0,0,0,0|2003,388,1,0,0,0,0|51419,18,0,0,0,0,0" GoodsID2="" Max="88" />
  <HuiGuiDayZhiGou ID="274" HuoDongLevel="3" TotalYuanBao="0,-1" Day="1" Price="1|11|7286" GoodsID1="2030,388,1,0,0,0,0|51419,18,0,0,0,0,0" GoodsID2="" Max="88" />
  <HuiGuiDayZhiGou ID="275" HuoDongLevel="3" TotalYuanBao="0,-1" Day="1" Price="1|2|7287" GoodsID1="2017,2888,1,0,0,0,0|2016,2388,1,0,0,0,0|51419,18,0,0,0,0,0" GoodsID2="" Max="88" />
  <HuiGuiDayZhiGou ID="276" HuoDongLevel="3" TotalYuanBao="0,-1" Day="1" Price="1|2|7288" GoodsID1="5050,2588,1,0,0,0,0|50305,18,1,0,0,0,0|50017,588,1,0,0,0,0|51419,18,0,0,0,0,0" GoodsID2="" Max="88" />
  <HuiGuiDayZhiGou ID="277" HuoDongLevel="3" TotalYuanBao="0,-1" Day="1" Price="1|14|7289" GoodsID1="2100,2588,1,0,0,0,0|5050,3888,1,0,0,0,0|5031,258,1,0,0,0,0|5041,258,1,0,0,0,0" GoodsID2="" Max="88" />
  <HuiGuiDayZhiGou ID="278" HuoDongLevel="3" TotalYuanBao="0,-1" Day="1" Price="1|16|7290" GoodsID1="7050,9888,1,0,0,0,0|50015,1588,1,0,0,0,0|5120,1088,1,0,0,0,0|51419,18,0,0,0,0,0" GoodsID2="" Max="88" />
  <HuiGuiDayZhiGou ID="279" HuoDongLevel="3" TotalYuanBao="0,-1" Day="1" Price="1|12|7291" GoodsID1="5120,628,1,0,0,0,0|7050,1888,1,0,0,0,0|51419,38,0,0,0,0,0" GoodsID2="" Max="88" />
  <HuiGuiDayZhiGou ID="280" HuoDongLevel="3" TotalYuanBao="0,-1" Day="1" Price="1|2|7292" GoodsID1="5312,108,1,0,0,0,0|7007,1688,1,0,0,0,0" GoodsID2="" Max="88" />
  <HuiGuiDayZhiGou ID="281" HuoDongLevel="3" TotalYuanBao="0,-1" Day="1" Price="1|14|7293" GoodsID1="63222,1,1,0,0,0,0|2103,688,1,0,0,0,0|2104,118,1,0,0,0,0" GoodsID2="" Max="88" />
  <HuiGuiDayZhiGou ID="282" HuoDongLevel="3" TotalYuanBao="0,-1" Day="1" Price="1|14|7294" GoodsID1="5331,100,1,0,0,0,0|5110,100,1,0,0,0,0|5220,100,1,0,0,0,0" GoodsID2="" Max="88" />
  <HuiGuiDayZhiGou ID="283" HuoDongLevel="3" TotalYuanBao="0,-1" Day="1" Price="1|16|7295" GoodsID1="5250,1688,1,0,0,0,0|2005,128,1,0,0,0,0" GoodsID2="" Max="88" />
  <HuiGuiDayZhiGou ID="284" HuoDongLevel="3" TotalYuanBao="0,-1" Day="1" Price="1|16|7296" GoodsID1="5284,288,1,0,0,0,0|5271,188,1,0,0,0,0" GoodsID2="" Max="88" />
  <HuiGuiDayZhiGou ID="285" HuoDongLevel="3" TotalYuanBao="0,-1" Day="1" Price="1|16|7297" GoodsID1="63215,1,1,0,0,0,0|51275,130,0,0,0,0,0" GoodsID2="" Max="88" />
  <HuiGuiDayZhiGou ID="286" HuoDongLevel="3" TotalYuanBao="0,-1" Day="1" Price="1|16|7298" GoodsID1="63201,1,1,0,0,0,0|51275,130,0,0,0,0,0" GoodsID2="" Max="88" />
  <HuiGuiDayZhiGou ID="287" HuoDongLevel="3" TotalYuanBao="0,-1" Day="1" Price="1|16|7299" GoodsID1="63203,1,1,0,0,0,0|51275,130,0,0,0,0,0" GoodsID2="" Max="88" />
  <HuiGuiDayZhiGou ID="288" HuoDongLevel="3" TotalYuanBao="0,-1" Day="1" Price="1|19|7300" GoodsID1="63216,1,1,0,0,0,0" GoodsID2="" Max="88" />
  <HuiGuiDayZhiGou ID="289" HuoDongLevel="3" TotalYuanBao="0,-1" Day="1" Price="1|19|7301" GoodsID1="63202,1,1,0,0,0,0" GoodsID2="" Max="88" />
  <HuiGuiDayZhiGou ID="290" HuoDongLevel="3" TotalYuanBao="0,-1" Day="2" Price="1|11|7302" GoodsID1="2001,388,1,0,0,0,0|2002,388,1,0,0,0,0|2003,388,1,0,0,0,0|51419,18,0,0,0,0,0" GoodsID2="" Max="88" />
  <HuiGuiDayZhiGou ID="291" HuoDongLevel="3" TotalYuanBao="0,-1" Day="2" Price="1|11|7303" GoodsID1="2030,388,1,0,0,0,0|51419,18,0,0,0,0,0" GoodsID2="" Max="88" />
  <HuiGuiDayZhiGou ID="292" HuoDongLevel="3" TotalYuanBao="0,-1" Day="2" Price="1|2|7304" GoodsID1="2017,2888,1,0,0,0,0|2016,2388,1,0,0,0,0|51419,18,0,0,0,0,0" GoodsID2="" Max="88" />
  <HuiGuiDayZhiGou ID="293" HuoDongLevel="3" TotalYuanBao="0,-1" Day="2" Price="1|2|7305" GoodsID1="5050,2588,1,0,0,0,0|50305,18,1,0,0,0,0|50017,588,1,0,0,0,0|51419,18,0,0,0,0,0" GoodsID2="" Max="88" />
  <HuiGuiDayZhiGou ID="294" HuoDongLevel="3" TotalYuanBao="0,-1" Day="2" Price="1|14|7306" GoodsID1="2100,2588,1,0,0,0,0|5050,3888,1,0,0,0,0|5031,258,1,0,0,0,0|5041,258,1,0,0,0,0" GoodsID2="" Max="88" />
  <HuiGuiDayZhiGou ID="295" HuoDongLevel="3" TotalYuanBao="0,-1" Day="2" Price="1|16|7307" GoodsID1="7050,9888,1,0,0,0,0|50015,1588,1,0,0,0,0|5120,1088,1,0,0,0,0|51419,18,0,0,0,0,0" GoodsID2="" Max="88" />
  <HuiGuiDayZhiGou ID="296" HuoDongLevel="3" TotalYuanBao="0,-1" Day="2" Price="1|12|7308" GoodsID1="5120,628,1,0,0,0,0|7050,1888,1,0,0,0,0|51419,38,0,0,0,0,0" GoodsID2="" Max="88" />
  <HuiGuiDayZhiGou ID="297" HuoDongLevel="3" TotalYuanBao="0,-1" Day="2" Price="1|2|7309" GoodsID1="5312,108,1,0,0,0,0|7007,1688,1,0,0,0,0" GoodsID2="" Max="88" />
  <HuiGuiDayZhiGou ID="298" HuoDongLevel="3" TotalYuanBao="0,-1" Day="2" Price="1|14|7310" GoodsID1="63222,1,1,0,0,0,0|2103,688,1,0,0,0,0|2104,118,1,0,0,0,0" GoodsID2="" Max="88" />
  <HuiGuiDayZhiGou ID="299" HuoDongLevel="3" TotalYuanBao="0,-1" Day="2" Price="1|14|7311" GoodsID1="5331,100,1,0,0,0,0|5110,100,1,0,0,0,0|5220,100,1,0,0,0,0" GoodsID2="" Max="88" />
  <HuiGuiDayZhiGou ID="300" HuoDongLevel="3" TotalYuanBao="0,-1" Day="2" Price="1|16|7312" GoodsID1="5250,1688,1,0,0,0,0|2005,128,1,0,0,0,0" GoodsID2="" Max="88" />
  <HuiGuiDayZhiGou ID="301" HuoDongLevel="3" TotalYuanBao="0,-1" Day="2" Price="1|16|7313" GoodsID1="5284,288,1,0,0,0,0|5271,188,1,0,0,0,0" GoodsID2="" Max="88" />
  <HuiGuiDayZhiGou ID="302" HuoDongLevel="3" TotalYuanBao="0,-1" Day="2" Price="1|16|7314" GoodsID1="63215,1,1,0,0,0,0|51275,130,0,0,0,0,0" GoodsID2="" Max="88" />
  <HuiGuiDayZhiGou ID="303" HuoDongLevel="3" TotalYuanBao="0,-1" Day="2" Price="1|16|7315" GoodsID1="63201,1,1,0,0,0,0|51275,130,0,0,0,0,0" GoodsID2="" Max="88" />
  <HuiGuiDayZhiGou ID="304" HuoDongLevel="3" TotalYuanBao="0,-1" Day="2" Price="1|16|7316" GoodsID1="63203,1,1,0,0,0,0|51275,130,0,0,0,0,0" GoodsID2="" Max="88" />
  <HuiGuiDayZhiGou ID="305" HuoDongLevel="3" TotalYuanBao="0,-1" Day="2" Price="1|19|7317" GoodsID1="63216,1,1,0,0,0,0" GoodsID2="" Max="88" />
  <HuiGuiDayZhiGou ID="306" HuoDongLevel="3" TotalYuanBao="0,-1" Day="2" Price="1|19|7318" GoodsID1="63202,1,1,0,0,0,0" GoodsID2="" Max="88" />
  <HuiGuiDayZhiGou ID="307" HuoDongLevel="3" TotalYuanBao="0,-1" Day="3" Price="1|11|7319" GoodsID1="2001,388,1,0,0,0,0|2002,388,1,0,0,0,0|2003,388,1,0,0,0,0|51419,18,0,0,0,0,0" GoodsID2="" Max="88" />
  <HuiGuiDayZhiGou ID="308" HuoDongLevel="3" TotalYuanBao="0,-1" Day="3" Price="1|11|7320" GoodsID1="2030,388,1,0,0,0,0|51419,18,0,0,0,0,0" GoodsID2="" Max="88" />
  <HuiGuiDayZhiGou ID="309" HuoDongLevel="3" TotalYuanBao="0,-1" Day="3" Price="1|2|7321" GoodsID1="2017,2888,1,0,0,0,0|2016,2388,1,0,0,0,0|51419,18,0,0,0,0,0" GoodsID2="" Max="88" />
  <HuiGuiDayZhiGou ID="310" HuoDongLevel="3" TotalYuanBao="0,-1" Day="3" Price="1|2|7322" GoodsID1="5050,2588,1,0,0,0,0|50305,18,1,0,0,0,0|50017,588,1,0,0,0,0|51419,18,0,0,0,0,0" GoodsID2="" Max="88" />
  <HuiGuiDayZhiGou ID="311" HuoDongLevel="3" TotalYuanBao="0,-1" Day="3" Price="1|14|7323" GoodsID1="2100,2588,1,0,0,0,0|5050,3888,1,0,0,0,0|5031,258,1,0,0,0,0|5041,258,1,0,0,0,0" GoodsID2="" Max="88" />
  <HuiGuiDayZhiGou ID="312" HuoDongLevel="3" TotalYuanBao="0,-1" Day="3" Price="1|16|7324" GoodsID1="7050,9888,1,0,0,0,0|50015,1588,1,0,0,0,0|5120,1088,1,0,0,0,0|51419,18,0,0,0,0,0" GoodsID2="" Max="88" />
  <HuiGuiDayZhiGou ID="313" HuoDongLevel="3" TotalYuanBao="0,-1" Day="3" Price="1|12|7325" GoodsID1="5120,628,1,0,0,0,0|7050,1888,1,0,0,0,0|51419,38,0,0,0,0,0" GoodsID2="" Max="88" />
  <HuiGuiDayZhiGou ID="314" HuoDongLevel="3" TotalYuanBao="0,-1" Day="3" Price="1|2|7326" GoodsID1="5312,108,1,0,0,0,0|7007,1688,1,0,0,0,0" GoodsID2="" Max="88" />
  <HuiGuiDayZhiGou ID="315" HuoDongLevel="3" TotalYuanBao="0,-1" Day="3" Price="1|14|7327" GoodsID1="63222,1,1,0,0,0,0|2103,688,1,0,0,0,0|2104,118,1,0,0,0,0" GoodsID2="" Max="88" />
  <HuiGuiDayZhiGou ID="316" HuoDongLevel="3" TotalYuanBao="0,-1" Day="3" Price="1|14|7328" GoodsID1="5331,100,1,0,0,0,0|5110,100,1,0,0,0,0|5220,100,1,0,0,0,0" GoodsID2="" Max="88" />
  <HuiGuiDayZhiGou ID="317" HuoDongLevel="3" TotalYuanBao="0,-1" Day="3" Price="1|16|7329" GoodsID1="5250,1688,1,0,0,0,0|2005,128,1,0,0,0,0" GoodsID2="" Max="88" />
  <HuiGuiDayZhiGou ID="318" HuoDongLevel="3" TotalYuanBao="0,-1" Day="3" Price="1|16|7330" GoodsID1="5284,288,1,0,0,0,0|5271,188,1,0,0,0,0" GoodsID2="" Max="88" />
  <HuiGuiDayZhiGou ID="319" HuoDongLevel="3" TotalYuanBao="0,-1" Day="3" Price="1|16|7331" GoodsID1="63215,1,1,0,0,0,0|51275,130,0,0,0,0,0" GoodsID2="" Max="88" />
  <HuiGuiDayZhiGou ID="320" HuoDongLevel="3" TotalYuanBao="0,-1" Day="3" Price="1|16|7332" GoodsID1="63201,1,1,0,0,0,0|51275,130,0,0,0,0,0" GoodsID2="" Max="88" />
  <HuiGuiDayZhiGou ID="321" HuoDongLevel="3" TotalYuanBao="0,-1" Day="3" Price="1|16|7333" GoodsID1="63203,1,1,0,0,0,0|51275,130,0,0,0,0,0" GoodsID2="" Max="88" />
  <HuiGuiDayZhiGou ID="322" HuoDongLevel="3" TotalYuanBao="0,-1" Day="3" Price="1|19|7334" GoodsID1="63216,1,1,0,0,0,0" GoodsID2="" Max="88" />
  <HuiGuiDayZhiGou ID="323" HuoDongLevel="3" TotalYuanBao="0,-1" Day="3" Price="1|19|7335" GoodsID1="63202,1,1,0,0,0,0" GoodsID2="" Max="88" />
  <HuiGuiDayZhiGou ID="324" HuoDongLevel="3" TotalYuanBao="0,-1" Day="4" Price="1|11|7336" GoodsID1="2001,388,1,0,0,0,0|2002,388,1,0,0,0,0|2003,388,1,0,0,0,0|51419,18,0,0,0,0,0" GoodsID2="" Max="88" />
  <HuiGuiDayZhiGou ID="325" HuoDongLevel="3" TotalYuanBao="0,-1" Day="4" Price="1|11|7337" GoodsID1="2030,388,1,0,0,0,0|51419,18,0,0,0,0,0" GoodsID2="" Max="88" />
  <HuiGuiDayZhiGou ID="326" HuoDongLevel="3" TotalYuanBao="0,-1" Day="4" Price="1|2|7338" GoodsID1="2017,2888,1,0,0,0,0|2016,2388,1,0,0,0,0|51419,18,0,0,0,0,0" GoodsID2="" Max="88" />
  <HuiGuiDayZhiGou ID="327" HuoDongLevel="3" TotalYuanBao="0,-1" Day="4" Price="1|2|7339" GoodsID1="5050,2588,1,0,0,0,0|50305,18,1,0,0,0,0|50017,588,1,0,0,0,0|51419,18,0,0,0,0,0" GoodsID2="" Max="88" />
  <HuiGuiDayZhiGou ID="328" HuoDongLevel="3" TotalYuanBao="0,-1" Day="4" Price="1|14|7340" GoodsID1="2100,2588,1,0,0,0,0|5050,3888,1,0,0,0,0|5031,258,1,0,0,0,0|5041,258,1,0,0,0,0" GoodsID2="" Max="88" />
  <HuiGuiDayZhiGou ID="329" HuoDongLevel="3" TotalYuanBao="0,-1" Day="4" Price="1|16|7341" GoodsID1="7050,9888,1,0,0,0,0|50015,1588,1,0,0,0,0|5120,1088,1,0,0,0,0|51419,18,0,0,0,0,0" GoodsID2="" Max="88" />
  <HuiGuiDayZhiGou ID="330" HuoDongLevel="3" TotalYuanBao="0,-1" Day="4" Price="1|12|7342" GoodsID1="5120,628,1,0,0,0,0|7050,1888,1,0,0,0,0|51419,38,0,0,0,0,0" GoodsID2="" Max="88" />
  <HuiGuiDayZhiGou ID="331" HuoDongLevel="3" TotalYuanBao="0,-1" Day="4" Price="1|2|7343" GoodsID1="5312,108,1,0,0,0,0|7007,1688,1,0,0,0,0" GoodsID2="" Max="88" />
  <HuiGuiDayZhiGou ID="332" HuoDongLevel="3" TotalYuanBao="0,-1" Day="4" Price="1|14|7344" GoodsID1="63222,1,1,0,0,0,0|2103,688,1,0,0,0,0|2104,118,1,0,0,0,0" GoodsID2="" Max="88" />
  <HuiGuiDayZhiGou ID="333" HuoDongLevel="3" TotalYuanBao="0,-1" Day="4" Price="1|14|7345" GoodsID1="5331,100,1,0,0,0,0|5110,100,1,0,0,0,0|5220,100,1,0,0,0,0" GoodsID2="" Max="88" />
  <HuiGuiDayZhiGou ID="334" HuoDongLevel="3" TotalYuanBao="0,-1" Day="4" Price="1|16|7346" GoodsID1="5250,1688,1,0,0,0,0|2005,128,1,0,0,0,0" GoodsID2="" Max="88" />
  <HuiGuiDayZhiGou ID="335" HuoDongLevel="3" TotalYuanBao="0,-1" Day="4" Price="1|16|7347" GoodsID1="5284,288,1,0,0,0,0|5271,188,1,0,0,0,0" GoodsID2="" Max="88" />
  <HuiGuiDayZhiGou ID="336" HuoDongLevel="3" TotalYuanBao="0,-1" Day="4" Price="1|16|7348" GoodsID1="63215,1,1,0,0,0,0|51275,130,0,0,0,0,0" GoodsID2="" Max="88" />
  <HuiGuiDayZhiGou ID="337" HuoDongLevel="3" TotalYuanBao="0,-1" Day="4" Price="1|16|7349" GoodsID1="63201,1,1,0,0,0,0|51275,130,0,0,0,0,0" GoodsID2="" Max="88" />
  <HuiGuiDayZhiGou ID="338" HuoDongLevel="3" TotalYuanBao="0,-1" Day="4" Price="1|16|7350" GoodsID1="63203,1,1,0,0,0,0|51275,130,0,0,0,0,0" GoodsID2="" Max="88" />
  <HuiGuiDayZhiGou ID="339" HuoDongLevel="3" TotalYuanBao="0,-1" Day="4" Price="1|19|7351" GoodsID1="63216,1,1,0,0,0,0" GoodsID2="" Max="88" />
  <HuiGuiDayZhiGou ID="340" HuoDongLevel="3" TotalYuanBao="0,-1" Day="4" Price="1|19|7352" GoodsID1="63202,1,1,0,0,0,0" GoodsID2="" Max="88" />
  <HuiGuiDayZhiGou ID="341" HuoDongLevel="3" TotalYuanBao="0,-1" Day="5" Price="1|11|7353" GoodsID1="2001,388,1,0,0,0,0|2002,388,1,0,0,0,0|2003,388,1,0,0,0,0|51419,18,0,0,0,0,0" GoodsID2="" Max="88" />
  <HuiGuiDayZhiGou ID="342" HuoDongLevel="3" TotalYuanBao="0,-1" Day="5" Price="1|11|7354" GoodsID1="2030,388,1,0,0,0,0|51419,18,0,0,0,0,0" GoodsID2="" Max="88" />
  <HuiGuiDayZhiGou ID="343" HuoDongLevel="3" TotalYuanBao="0,-1" Day="5" Price="1|2|7355" GoodsID1="2017,2888,1,0,0,0,0|2016,2388,1,0,0,0,0|51419,18,0,0,0,0,0" GoodsID2="" Max="88" />
  <HuiGuiDayZhiGou ID="344" HuoDongLevel="3" TotalYuanBao="0,-1" Day="5" Price="1|2|7356" GoodsID1="5050,2588,1,0,0,0,0|50305,18,1,0,0,0,0|50017,588,1,0,0,0,0|51419,18,0,0,0,0,0" GoodsID2="" Max="88" />
  <HuiGuiDayZhiGou ID="345" HuoDongLevel="3" TotalYuanBao="0,-1" Day="5" Price="1|14|7357" GoodsID1="2100,2588,1,0,0,0,0|5050,3888,1,0,0,0,0|5031,258,1,0,0,0,0|5041,258,1,0,0,0,0" GoodsID2="" Max="88" />
  <HuiGuiDayZhiGou ID="346" HuoDongLevel="3" TotalYuanBao="0,-1" Day="5" Price="1|16|7358" GoodsID1="7050,9888,1,0,0,0,0|50015,1588,1,0,0,0,0|5120,1088,1,0,0,0,0|51419,18,0,0,0,0,0" GoodsID2="" Max="88" />
  <HuiGuiDayZhiGou ID="347" HuoDongLevel="3" TotalYuanBao="0,-1" Day="5" Price="1|12|7359" GoodsID1="5120,628,1,0,0,0,0|7050,1888,1,0,0,0,0|51419,38,0,0,0,0,0" GoodsID2="" Max="88" />
  <HuiGuiDayZhiGou ID="348" HuoDongLevel="3" TotalYuanBao="0,-1" Day="5" Price="1|2|7360" GoodsID1="5312,108,1,0,0,0,0|7007,1688,1,0,0,0,0" GoodsID2="" Max="88" />
  <HuiGuiDayZhiGou ID="349" HuoDongLevel="3" TotalYuanBao="0,-1" Day="5" Price="1|14|7361" GoodsID1="63222,1,1,0,0,0,0|2103,688,1,0,0,0,0|2104,118,1,0,0,0,0" GoodsID2="" Max="88" />
  <HuiGuiDayZhiGou ID="350" HuoDongLevel="3" TotalYuanBao="0,-1" Day="5" Price="1|14|7362" GoodsID1="5331,100,1,0,0,0,0|5110,100,1,0,0,0,0|5220,100,1,0,0,0,0" GoodsID2="" Max="88" />
  <HuiGuiDayZhiGou ID="351" HuoDongLevel="3" TotalYuanBao="0,-1" Day="5" Price="1|16|7363" GoodsID1="5250,1688,1,0,0,0,0|2005,128,1,0,0,0,0" GoodsID2="" Max="88" />
  <HuiGuiDayZhiGou ID="352" HuoDongLevel="3" TotalYuanBao="0,-1" Day="5" Price="1|16|7364" GoodsID1="5284,288,1,0,0,0,0|5271,188,1,0,0,0,0" GoodsID2="" Max="88" />
  <HuiGuiDayZhiGou ID="353" HuoDongLevel="3" TotalYuanBao="0,-1" Day="5" Price="1|16|7365" GoodsID1="63215,1,1,0,0,0,0|51275,130,0,0,0,0,0" GoodsID2="" Max="88" />
  <HuiGuiDayZhiGou ID="354" HuoDongLevel="3" TotalYuanBao="0,-1" Day="5" Price="1|16|7366" GoodsID1="63201,1,1,0,0,0,0|51275,130,0,0,0,0,0" GoodsID2="" Max="88" />
  <HuiGuiDayZhiGou ID="355" HuoDongLevel="3" TotalYuanBao="0,-1" Day="5" Price="1|16|7367" GoodsID1="63203,1,1,0,0,0,0|51275,130,0,0,0,0,0" GoodsID2="" Max="88" />
  <HuiGuiDayZhiGou ID="356" HuoDongLevel="3" TotalYuanBao="0,-1" Day="5" Price="1|19|7368" GoodsID1="63216,1,1,0,0,0,0" GoodsID2="" Max="88" />
  <HuiGuiDayZhiGou ID="357" HuoDongLevel="3" TotalYuanBao="0,-1" Day="5" Price="1|19|7369" GoodsID1="63202,1,1,0,0,0,0" GoodsID2="" Max="88" />
  <HuiGuiDayZhiGou ID="358" HuoDongLevel="3" TotalYuanBao="0,-1" Day="6" Price="1|11|7370" GoodsID1="2001,388,1,0,0,0,0|2002,388,1,0,0,0,0|2003,388,1,0,0,0,0|51419,18,0,0,0,0,0" GoodsID2="" Max="88" />
  <HuiGuiDayZhiGou ID="359" HuoDongLevel="3" TotalYuanBao="0,-1" Day="6" Price="1|11|7371" GoodsID1="2030,388,1,0,0,0,0|51419,18,0,0,0,0,0" GoodsID2="" Max="88" />
  <HuiGuiDayZhiGou ID="360" HuoDongLevel="3" TotalYuanBao="0,-1" Day="6" Price="1|2|7372" GoodsID1="2017,2888,1,0,0,0,0|2016,2388,1,0,0,0,0|51419,18,0,0,0,0,0" GoodsID2="" Max="88" />
  <HuiGuiDayZhiGou ID="361" HuoDongLevel="3" TotalYuanBao="0,-1" Day="6" Price="1|2|7373" GoodsID1="5050,2588,1,0,0,0,0|50305,18,1,0,0,0,0|50017,588,1,0,0,0,0|51419,18,0,0,0,0,0" GoodsID2="" Max="88" />
  <HuiGuiDayZhiGou ID="362" HuoDongLevel="3" TotalYuanBao="0,-1" Day="6" Price="1|14|7374" GoodsID1="2100,2588,1,0,0,0,0|5050,3888,1,0,0,0,0|5031,258,1,0,0,0,0|5041,258,1,0,0,0,0" GoodsID2="" Max="88" />
  <HuiGuiDayZhiGou ID="363" HuoDongLevel="3" TotalYuanBao="0,-1" Day="6" Price="1|16|7375" GoodsID1="7050,9888,1,0,0,0,0|50015,1588,1,0,0,0,0|5120,1088,1,0,0,0,0|51419,18,0,0,0,0,0" GoodsID2="" Max="88" />
  <HuiGuiDayZhiGou ID="364" HuoDongLevel="3" TotalYuanBao="0,-1" Day="6" Price="1|12|7376" GoodsID1="5120,628,1,0,0,0,0|7050,1888,1,0,0,0,0|51419,38,0,0,0,0,0" GoodsID2="" Max="88" />
  <HuiGuiDayZhiGou ID="365" HuoDongLevel="3" TotalYuanBao="0,-1" Day="6" Price="1|2|7377" GoodsID1="5312,108,1,0,0,0,0|7007,1688,1,0,0,0,0" GoodsID2="" Max="88" />
  <HuiGuiDayZhiGou ID="366" HuoDongLevel="3" TotalYuanBao="0,-1" Day="6" Price="1|14|7378" GoodsID1="63222,1,1,0,0,0,0|2103,688,1,0,0,0,0|2104,118,1,0,0,0,0" GoodsID2="" Max="88" />
  <HuiGuiDayZhiGou ID="367" HuoDongLevel="3" TotalYuanBao="0,-1" Day="6" Price="1|14|7379" GoodsID1="5331,100,1,0,0,0,0|5110,100,1,0,0,0,0|5220,100,1,0,0,0,0" GoodsID2="" Max="88" />
  <HuiGuiDayZhiGou ID="368" HuoDongLevel="3" TotalYuanBao="0,-1" Day="6" Price="1|16|7380" GoodsID1="5250,1688,1,0,0,0,0|2005,128,1,0,0,0,0" GoodsID2="" Max="88" />
  <HuiGuiDayZhiGou ID="369" HuoDongLevel="3" TotalYuanBao="0,-1" Day="6" Price="1|16|7381" GoodsID1="5284,288,1,0,0,0,0|5271,188,1,0,0,0,0" GoodsID2="" Max="88" />
  <HuiGuiDayZhiGou ID="370" HuoDongLevel="3" TotalYuanBao="0,-1" Day="6" Price="1|16|7382" GoodsID1="63215,1,1,0,0,0,0|51275,130,0,0,0,0,0" GoodsID2="" Max="88" />
  <HuiGuiDayZhiGou ID="371" HuoDongLevel="3" TotalYuanBao="0,-1" Day="6" Price="1|16|7383" GoodsID1="63201,1,1,0,0,0,0|51275,130,0,0,0,0,0" GoodsID2="" Max="88" />
  <HuiGuiDayZhiGou ID="372" HuoDongLevel="3" TotalYuanBao="0,-1" Day="6" Price="1|16|7384" GoodsID1="63203,1,1,0,0,0,0|51275,130,0,0,0,0,0" GoodsID2="" Max="88" />
  <HuiGuiDayZhiGou ID="373" HuoDongLevel="3" TotalYuanBao="0,-1" Day="6" Price="1|19|7385" GoodsID1="63216,1,1,0,0,0,0" GoodsID2="" Max="88" />
  <HuiGuiDayZhiGou ID="374" HuoDongLevel="3" TotalYuanBao="0,-1" Day="6" Price="1|19|7386" GoodsID1="63202,1,1,0,0,0,0" GoodsID2="" Max="88" />
  <HuiGuiDayZhiGou ID="375" HuoDongLevel="3" TotalYuanBao="0,-1" Day="7" Price="1|11|7387" GoodsID1="2001,388,1,0,0,0,0|2002,388,1,0,0,0,0|2003,388,1,0,0,0,0|51419,18,0,0,0,0,0" GoodsID2="" Max="88" />
  <HuiGuiDayZhiGou ID="376" HuoDongLevel="3" TotalYuanBao="0,-1" Day="7" Price="1|11|7388" GoodsID1="2030,388,1,0,0,0,0|51419,18,0,0,0,0,0" GoodsID2="" Max="88" />
  <HuiGuiDayZhiGou ID="377" HuoDongLevel="3" TotalYuanBao="0,-1" Day="7" Price="1|2|7389" GoodsID1="2017,2888,1,0,0,0,0|2016,2388,1,0,0,0,0|51419,18,0,0,0,0,0" GoodsID2="" Max="88" />
  <HuiGuiDayZhiGou ID="378" HuoDongLevel="3" TotalYuanBao="0,-1" Day="7" Price="1|2|7390" GoodsID1="5050,2588,1,0,0,0,0|50305,18,1,0,0,0,0|50017,588,1,0,0,0,0|51419,18,0,0,0,0,0" GoodsID2="" Max="88" />
  <HuiGuiDayZhiGou ID="379" HuoDongLevel="3" TotalYuanBao="0,-1" Day="7" Price="1|14|7391" GoodsID1="2100,2588,1,0,0,0,0|5050,3888,1,0,0,0,0|5031,258,1,0,0,0,0|5041,258,1,0,0,0,0" GoodsID2="" Max="88" />
  <HuiGuiDayZhiGou ID="380" HuoDongLevel="3" TotalYuanBao="0,-1" Day="7" Price="1|16|7392" GoodsID1="7050,9888,1,0,0,0,0|50015,1588,1,0,0,0,0|5120,1088,1,0,0,0,0|51419,18,0,0,0,0,0" GoodsID2="" Max="88" />
  <HuiGuiDayZhiGou ID="381" HuoDongLevel="3" TotalYuanBao="0,-1" Day="7" Price="1|12|7393" GoodsID1="5120,628,1,0,0,0,0|7050,1888,1,0,0,0,0|51419,38,0,0,0,0,0" GoodsID2="" Max="88" />
  <HuiGuiDayZhiGou ID="382" HuoDongLevel="3" TotalYuanBao="0,-1" Day="7" Price="1|2|7394" GoodsID1="5312,108,1,0,0,0,0|7007,1688,1,0,0,0,0" GoodsID2="" Max="88" />
  <HuiGuiDayZhiGou ID="383" HuoDongLevel="3" TotalYuanBao="0,-1" Day="7" Price="1|14|7395" GoodsID1="63222,1,1,0,0,0,0|2103,688,1,0,0,0,0|2104,118,1,0,0,0,0" GoodsID2="" Max="88" />
  <HuiGuiDayZhiGou ID="384" HuoDongLevel="3" TotalYuanBao="0,-1" Day="7" Price="1|14|7396" GoodsID1="5331,100,1,0,0,0,0|5110,100,1,0,0,0,0|5220,100,1,0,0,0,0" GoodsID2="" Max="88" />
  <HuiGuiDayZhiGou ID="385" HuoDongLevel="3" TotalYuanBao="0,-1" Day="7" Price="1|16|7397" GoodsID1="5250,1688,1,0,0,0,0|2005,128,1,0,0,0,0" GoodsID2="" Max="88" />
  <HuiGuiDayZhiGou ID="386" HuoDongLevel="3" TotalYuanBao="0,-1" Day="7" Price="1|16|7398" GoodsID1="5284,288,1,0,0,0,0|5271,188,1,0,0,0,0" GoodsID2="" Max="88" />
  <HuiGuiDayZhiGou ID="387" HuoDongLevel="3" TotalYuanBao="0,-1" Day="7" Price="1|16|7399" GoodsID1="63215,1,1,0,0,0,0|51275,130,0,0,0,0,0" GoodsID2="" Max="88" />
  <HuiGuiDayZhiGou ID="388" HuoDongLevel="3" TotalYuanBao="0,-1" Day="7" Price="1|16|7400" GoodsID1="63201,1,1,0,0,0,0|51275,130,0,0,0,0,0" GoodsID2="" Max="88" />
  <HuiGuiDayZhiGou ID="389" HuoDongLevel="3" TotalYuanBao="0,-1" Day="7" Price="1|16|7401" GoodsID1="63203,1,1,0,0,0,0|51275,130,0,0,0,0,0" GoodsID2="" Max="88" />
  <HuiGuiDayZhiGou ID="390" HuoDongLevel="3" TotalYuanBao="0,-1" Day="7" Price="1|19|7402" GoodsID1="63216,1,1,0,0,0,0" GoodsID2="" Max="88" />
  <HuiGuiDayZhiGou ID="391" HuoDongLevel="3" TotalYuanBao="0,-1" Day="7" Price="1|19|7403" GoodsID1="63202,1,1,0,0,0,0" GoodsID2="" Max="88" />
  <HuiGuiDayZhiGou ID="392" HuoDongLevel="3" TotalYuanBao="0,-1" Day="8" Price="1|11|7404" GoodsID1="2001,388,1,0,0,0,0|2002,388,1,0,0,0,0|2003,388,1,0,0,0,0|51419,18,0,0,0,0,0" GoodsID2="" Max="88" />
  <HuiGuiDayZhiGou ID="393" HuoDongLevel="3" TotalYuanBao="0,-1" Day="8" Price="1|11|7405" GoodsID1="2030,388,1,0,0,0,0|51419,18,0,0,0,0,0" GoodsID2="" Max="88" />
  <HuiGuiDayZhiGou ID="394" HuoDongLevel="3" TotalYuanBao="0,-1" Day="8" Price="1|2|7406" GoodsID1="2017,2888,1,0,0,0,0|2016,2388,1,0,0,0,0|51419,18,0,0,0,0,0" GoodsID2="" Max="88" />
  <HuiGuiDayZhiGou ID="395" HuoDongLevel="3" TotalYuanBao="0,-1" Day="8" Price="1|2|7407" GoodsID1="5050,2588,1,0,0,0,0|50305,18,1,0,0,0,0|50017,588,1,0,0,0,0|51419,18,0,0,0,0,0" GoodsID2="" Max="88" />
  <HuiGuiDayZhiGou ID="396" HuoDongLevel="3" TotalYuanBao="0,-1" Day="8" Price="1|14|7408" GoodsID1="2100,2588,1,0,0,0,0|5050,3888,1,0,0,0,0|5031,258,1,0,0,0,0|5041,258,1,0,0,0,0" GoodsID2="" Max="88" />
  <HuiGuiDayZhiGou ID="397" HuoDongLevel="3" TotalYuanBao="0,-1" Day="8" Price="1|16|7409" GoodsID1="7050,9888,1,0,0,0,0|50015,1588,1,0,0,0,0|5120,1088,1,0,0,0,0|51419,18,0,0,0,0,0" GoodsID2="" Max="88" />
  <HuiGuiDayZhiGou ID="398" HuoDongLevel="3" TotalYuanBao="0,-1" Day="8" Price="1|12|7410" GoodsID1="5120,628,1,0,0,0,0|7050,1888,1,0,0,0,0|51419,38,0,0,0,0,0" GoodsID2="" Max="88" />
  <HuiGuiDayZhiGou ID="399" HuoDongLevel="3" TotalYuanBao="0,-1" Day="8" Price="1|2|7411" GoodsID1="5312,108,1,0,0,0,0|7007,1688,1,0,0,0,0" GoodsID2="" Max="88" />
  <HuiGuiDayZhiGou ID="400" HuoDongLevel="3" TotalYuanBao="0,-1" Day="8" Price="1|14|7412" GoodsID1="63222,1,1,0,0,0,0|2103,688,1,0,0,0,0|2104,118,1,0,0,0,0" GoodsID2="" Max="88" />
  <HuiGuiDayZhiGou ID="401" HuoDongLevel="3" TotalYuanBao="0,-1" Day="8" Price="1|14|7413" GoodsID1="5331,100,1,0,0,0,0|5110,100,1,0,0,0,0|5220,100,1,0,0,0,0" GoodsID2="" Max="88" />
  <HuiGuiDayZhiGou ID="402" HuoDongLevel="3" TotalYuanBao="0,-1" Day="8" Price="1|16|7414" GoodsID1="5250,1688,1,0,0,0,0|2005,128,1,0,0,0,0" GoodsID2="" Max="88" />
  <HuiGuiDayZhiGou ID="403" HuoDongLevel="3" TotalYuanBao="0,-1" Day="8" Price="1|16|7415" GoodsID1="5284,288,1,0,0,0,0|5271,188,1,0,0,0,0" GoodsID2="" Max="88" />
  <HuiGuiDayZhiGou ID="404" HuoDongLevel="3" TotalYuanBao="0,-1" Day="8" Price="1|16|7416" GoodsID1="63215,1,1,0,0,0,0|51275,130,0,0,0,0,0" GoodsID2="" Max="88" />
  <HuiGuiDayZhiGou ID="405" HuoDongLevel="3" TotalYuanBao="0,-1" Day="8" Price="1|16|7417" GoodsID1="63201,1,1,0,0,0,0|51275,130,0,0,0,0,0" GoodsID2="" Max="88" />
  <HuiGuiDayZhiGou ID="406" HuoDongLevel="3" TotalYuanBao="0,-1" Day="8" Price="1|16|7418" GoodsID1="63203,1,1,0,0,0,0|51275,130,0,0,0,0,0" GoodsID2="" Max="88" />
  <HuiGuiDayZhiGou ID="407" HuoDongLevel="3" TotalYuanBao="0,-1" Day="8" Price="1|19|7419" GoodsID1="63216,1,1,0,0,0,0" GoodsID2="" Max="88" />
  <HuiGuiDayZhiGou ID="408" HuoDongLevel="3" TotalYuanBao="0,-1" Day="8" Price="1|19|7420" GoodsID1="63202,1,1,0,0,0,0" GoodsID2="" Max="88" />
</Config>